[
  {
    "ean": "5010622005012",
    "asin": "B07P2TZDKH",
    "name": "Oral-B EssentialFloss 2 x 50m Cavity Defence Floss",
    "supplier_cost": 1.476,
    "amazon_price": 8.05,
    "fees": 4.04,
    "profit": 2.5340000000000007,
    "roi": 171.68021680216808,
    "estimated_sales": 50.0,
    "amazon_link": "https://www.amazon.fr/gp/product/B074F5NNCP/ref=xx_dp_cont_revecalc",
    "supplier_link": "https://www.qogita.com/products/5MRB7JjTkK/oralb-essential-floss-mint-50-m-dental-floss/",
    "sas_link": "https://sas.selleramp.com/sas/lookup?SasLookup%5Bsearch_term%5D=B07P2TZDKH",
    "image_url": "https://m.media-amazon.com/images/I/41+YagIzDwS._SL120_.jpg",
    "posted": true,
    "posted_at": "2026-03-24T09:45:55.414269+00:00",
    "created_at": "2026-03-24T05:18:57.391150+00:00"
  },
  {
    "ean": "0070942122511",
    "asin": "B002WZB2TE",
    "name": "Gum 317 Cepillo delicado, colours aleatorios",
    "supplier_cost": 2.268,
    "amazon_price": 9.2,
    "fees": 5.88,
    "profit": 1.0519999999999996,
    "roi": 46.384479717813036,
    "estimated_sales": 5.0,
    "amazon_link": "https://www.amazon.fr/gp/product/B002WZB2TE/ref=xx_dp_cont_revecalc",
    "supplier_link": "https://www.qogita.com/products/3KqmQHSjNF/eraser-delicate-post-operation-toothbrush/",
    "sas_link": "https://sas.selleramp.com/sas/lookup?SasLookup%5Bsearch_term%5D=B002WZB2TE",
    "image_url": "https://m.media-amazon.com/images/I/31nSbK+DViL._SL120_.jpg",
    "posted": true,
    "posted_at": "2026-03-24T09:46:19.380411+00:00",
    "created_at": "2026-03-24T05:18:57.445453+00:00"
  },
  {
    "ean": "3577057054470",
    "asin": "B00DHEKA6U",
    "name": "ELGYDIUM VITALE Toothbrush MEDIUM (1 brush)",
    "supplier_cost": 2.976,
    "amazon_price": 9.17,
    "fees": 4.09,
    "profit": 2.104,
    "roi": 70.6989247311828,
    "estimated_sales": 13.0,
    "amazon_link": "https://www.amazon.fr/gp/product/B00DHEKA6U/ref=xx_dp_cont_revecalc",
    "supplier_link": "https://www.qogita.com/products/2ZYQYY/elgydium-vitale-medium-toothbrush-for-plaque-removal/",
    "sas_link": "https://sas.selleramp.com/sas/lookup?SasLookup%5Bsearch_term%5D=B00DHEKA6U",
    "image_url": "https://m.media-amazon.com/images/I/31j-IESKelL._SL120_.jpg",
    "posted": true,
    "posted_at": "2026-03-24T09:46:39.741319+00:00",
    "created_at": "2026-03-24T05:19:14.965880+00:00"
  },
  {
    "ean": "3574661745008",
    "asin": "B0CZ9H71JG",
    "name": "Listerine Cool Mint Mild 95ml",
    "supplier_cost": 0.876,
    "amazon_price": 9.99,
    "fees": 5.93,
    "profit": 3.1840000000000006,
    "roi": 363.4703196347033,
    "estimated_sales": 5.0,
    "amazon_link": "https://www.amazon.fr/gp/product/B0CZ9H71JG/ref=xx_dp_cont_revecalc",
    "supplier_link": "https://www.qogita.com/products/b8d48870ba9046eebee73944e6bb25cc/listerine-mouthwash-95ml-coolmint-without-alcohol/",
    "sas_link": "https://sas.selleramp.com/sas/lookup?SasLookup%5Bsearch_term%5D=B0CZ9H71JG",
    "image_url": "https://m.media-amazon.com/images/I/313ONRVwN1L._SL120_.jpg",
    "posted": true,
    "posted_at": "2026-03-24T09:47:06.097472+00:00",
    "created_at": "2026-03-24T05:19:15.034435+00:00"
  },
  {
    "ean": "7630019905107",
    "asin": "B0BTZYNNSF",
    "name": "GUM Twisted Floss",
    "supplier_cost": 2.916,
    "amazon_price": 8.26,
    "fees": 4.01,
    "profit": 1.334,
    "roi": 45.74759945130316,
    "estimated_sales": 6.0,
    "amazon_link": "https://www.amazon.fr/gp/product/B0BTZYNNSF/ref=xx_dp_cont_revecalc",
    "supplier_link": "https://www.qogita.com/products/467XEQ/gum-sunstar-gum-gum-twisted-floss-dental-floss-30-m/",
    "sas_link": "https://sas.selleramp.com/sas/lookup?SasLookup%5Bsearch_term%5D=B0BTZYNNSF",
    "image_url": "https://m.media-amazon.com/images/I/51Yy6vmWwLL._SL120_.jpg",
    "posted": true,
    "posted_at": "2026-03-24T09:47:22.616780+00:00",
    "created_at": "2026-03-24T05:19:15.172098+00:00"
  },
  {
    "ean": "0070942304795",
    "asin": "B009UU83GO",
    "name": "Gum ortho toothpaste gel 75ml",
    "supplier_cost": 1.944,
    "amazon_price": 9.1,
    "fees": 5.87,
    "profit": 1.2859999999999996,
    "roi": 66.15226337448557,
    "estimated_sales": 50.0,
    "amazon_link": "https://www.amazon.fr/gp/product/B009UU83GO/ref=xx_dp_cont_revecalc",
    "supplier_link": "https://www.qogita.com/products/5n6xVrRhw7/gum-ortho-pasta-dent-75ml/",
    "sas_link": "https://sas.selleramp.com/sas/lookup?SasLookup%5Bsearch_term%5D=B009UU83GO",
    "image_url": "https://m.media-amazon.com/images/I/31lgMcBCjRL._SL120_.jpg",
    "posted": true,
    "posted_at": "2026-03-24T09:47:45.857506+00:00",
    "created_at": "2026-03-24T05:19:36.721476+00:00"
  },
  {
    "ean": "0070942302777",
    "asin": "B002WDMP3I",
    "name": "GUM Double Action Tongue Scraper",
    "supplier_cost": 2.052,
    "amazon_price": 7.16,
    "fees": 3.95,
    "profit": 1.158,
    "roi": 56.43274853801169,
    "estimated_sales": 100.0,
    "amazon_link": "https://www.amazon.fr/gp/product/B002WDMP3I/ref=xx_dp_cont_revecalc",
    "supplier_link": "https://www.qogita.com/products/3pbzBdpreh/eraser-tongue-cleaner-1-piece/",
    "sas_link": "https://sas.selleramp.com/sas/lookup?SasLookup%5Bsearch_term%5D=B002WDMP3I",
    "image_url": "https://m.media-amazon.com/images/I/31Q7aOMnf2L._SL120_.jpg",
    "posted": true,
    "posted_at": "2026-03-24T09:48:08.492171+00:00",
    "created_at": "2026-03-24T05:19:48.093515+00:00"
  },
  {
    "ean": "8017331060735",
    "asin": "B07JZBJKM3",
    "name": "Biorepair, High Density Mouthwash Gum Protection with Hyaluronic Acid & Antibacterial Zinc Helps Prevent Ginger Bleeding, Fluoride, Alcohol & Chlorhexidine Free, 500ml",
    "supplier_cost": 4.02,
    "amazon_price": 15.05,
    "fees": 9.37,
    "profit": 1.660000000000002,
    "roi": 41.29353233830851,
    "estimated_sales": 22.0,
    "amazon_link": "https://www.amazon.fr/gp/product/B07JZBJKM3/ref=xx_dp_cont_revecalc",
    "supplier_link": "https://www.qogita.com/products/074Z0Q/biorepair-antibacterial-mouthwash-gum-protection/",
    "sas_link": "https://sas.selleramp.com/sas/lookup?SasLookup%5Bsearch_term%5D=B07JZBJKM3",
    "image_url": "https://m.media-amazon.com/images/I/41cuQE8aKtL._SL120_.jpg",
    "posted": true,
    "posted_at": "2026-03-24T09:48:33.053565+00:00",
    "created_at": "2026-03-24T05:19:48.097059+00:00"
  },
  {
    "ean": "8006540582749",
    "asin": "B09Q9813L6",
    "name": "Always Platinum Sanitary Napkins, Size 1, Normal, 96 Towels with Wings, Light Day Fluxes, Eco Size, Soft & Flexible, Super Absorbent & Ultra Thin",
    "supplier_cost": 5.268,
    "amazon_price": 21.47,
    "fees": 11.29,
    "profit": 4.912,
    "roi": 93.2422171602126,
    "estimated_sales": 50.0,
    "amazon_link": "https://www.amazon.fr/gp/product/B09Q9813L6/ref=xx_dp_cont_revecalc",
    "supplier_link": "https://www.qogita.com/products/K41653/always-platinum-damenbinden-with-wings-normal-plus-eco-5-comfort-sizes-size-1/",
    "sas_link": "https://sas.selleramp.com/sas/lookup?SasLookup%5Bsearch_term%5D=B09Q9813L6",
    "image_url": "https://m.media-amazon.com/images/I/51vX7oFYvXL._SL120_.jpg",
    "posted": true,
    "posted_at": "2026-03-24T09:48:51.278925+00:00",
    "created_at": "2026-03-24T05:19:49.369624+00:00"
  },
  {
    "ean": "0070942502016",
    "asin": "B00D7BFIQK",
    "name": "2GUM Denture Brush with Double Hard Brush Head",
    "supplier_cost": 2.136,
    "amazon_price": 7.99,
    "fees": 4.02,
    "profit": 1.8340000000000005,
    "roi": 85.8614232209738,
    "estimated_sales": 10.0,
    "amazon_link": "https://www.amazon.fr/gp/product/B00D7BFIQK/ref=xx_dp_cont_revecalc",
    "supplier_link": "https://www.qogita.com/products/4VozyTRYhz/green-gum-prosthesis-brush/",
    "sas_link": "https://sas.selleramp.com/sas/lookup?SasLookup%5Bsearch_term%5D=B00D7BFIQK",
    "image_url": "https://m.media-amazon.com/images/I/41wIYMafThL._SL120_.jpg",
    "posted": true,
    "posted_at": "2026-03-24T09:49:18.637580+00:00",
    "created_at": "2026-03-24T05:20:03.010167+00:00"
  },
  {
    "ean": "8700216539128",
    "asin": "B08F78FX66",
    "name": "Oral-B Superfloss Thread Threaders Pack of 2 x 50 Strands - Removes Plaque and Tartar - Dental Floss for Braces",
    "supplier_cost": 2.076,
    "amazon_price": 9.9,
    "fees": 4.15,
    "profit": 3.674,
    "roi": 176.97495183044316,
    "estimated_sales": 40.0,
    "amazon_link": "https://www.amazon.fr/gp/product/B08F78FX66/ref=xx_dp_cont_revecalc",
    "supplier_link": "https://www.qogita.com/products/0f50c6d249d846119440153637f59230/oral-b-superfloss-regular-threader/",
    "sas_link": "https://sas.selleramp.com/sas/lookup?SasLookup%5Bsearch_term%5D=B08F78FX66",
    "image_url": "https://m.media-amazon.com/images/I/416APD64UbL._SL120_.jpg",
    "posted": true,
    "posted_at": "2026-03-24T09:49:34.400068+00:00",
    "created_at": "2026-03-24T05:20:03.014999+00:00"
  },
  {
    "ean": "3401560503067",
    "asin": "B00XO1WYN8",
    "name": "LACTIBIANE TRAVEL 14 CAPSULES PILEJE",
    "supplier_cost": 10.824,
    "amazon_price": 22.6,
    "fees": 9.05,
    "profit": 2.726000000000001,
    "roi": 25.184774575018487,
    "estimated_sales": 19.0,
    "amazon_link": "https://www.amazon.fr/gp/product/B00XO1WYN8/ref=xx_dp_cont_revecalc",
    "supplier_link": "https://www.qogita.com/products/GToYxnRHeW/pileje-lactibiane-voyage-14-capsules/",
    "sas_link": "https://sas.selleramp.com/sas/lookup?SasLookup%5Bsearch_term%5D=B00XO1WYN8",
    "image_url": "https://m.media-amazon.com/images/I/41L3Wx7VEaL._SL120_.jpg",
    "posted": true,
    "posted_at": "2026-03-24T09:50:03.711306+00:00",
    "created_at": "2026-03-24T05:20:03.023106+00:00"
  },
  {
    "ean": "6001067007289",
    "asin": "B01EO0Q7BW",
    "name": "Colgate Double Action Toothbrush, Medium, 18 cm, Pack of 12",
    "supplier_cost": 0.444,
    "amazon_price": 17.99,
    "fees": 9.91,
    "profit": 7.635999999999998,
    "roi": 1719.8198198198195,
    "estimated_sales": 13.0,
    "amazon_link": "https://www.amazon.fr/gp/product/B01EO0Q7BW/ref=xx_dp_cont_revecalc",
    "supplier_link": "https://www.qogita.com/products/FVPZUDZiQt/colgate-double-action-toothbrush-medium-18cm/",
    "sas_link": "https://sas.selleramp.com/sas/lookup?SasLookup%5Bsearch_term%5D=B01EO0Q7BW",
    "image_url": "https://m.media-amazon.com/images/I/51+xCxWYPkL._SL120_.jpg",
    "posted": true,
    "posted_at": "2026-03-24T09:50:28.593302+00:00",
    "created_at": "2026-03-24T05:20:03.045252+00:00"
  },
  {
    "ean": "7317400015422",
    "asin": "B015D4MVWM",
    "name": "TePe Interdental Brush Original, Green, 0.8mm/ISO 5, 8 pieces, plaque removal, effective cleaning between teeth, floss, for small spaces",
    "supplier_cost": 3.972,
    "amazon_price": 11.99,
    "fees": 5.19,
    "profit": 2.828,
    "roi": 71.19838872104732,
    "estimated_sales": 2373.0,
    "amazon_link": "https://www.amazon.fr/gp/product/B015D4MVWM/ref=xx_dp_cont_revecalc",
    "supplier_link": "https://www.qogita.com/products/8BRR3g53hN/tepe-interdental-brush-normal-08-mm-green-8-pieces/",
    "sas_link": "https://sas.selleramp.com/sas/lookup?SasLookup%5Bsearch_term%5D=B015D4MVWM",
    "image_url": "https://m.media-amazon.com/images/I/41cmykwLY6L._SL120_.jpg",
    "posted": true,
    "posted_at": "2026-03-24T09:50:51.332440+00:00",
    "created_at": "2026-03-24T05:20:14.398408+00:00"
  },
  {
    "ean": "5060565101395",
    "asin": "B0837B84W7",
    "name": "REVOX B77 - Just Salicylic Acid 2%, 30 ml, Salicylic Acid Serum, Face Peeling, For Oily Skin, Combination And Acne Skin, Deep Cleansing Exfoliant, Regulates Excess Sebum",
    "supplier_cost": 3.9,
    "amazon_price": 13.12,
    "fees": 7.58,
    "profit": 1.6399999999999992,
    "roi": 42.05128205128204,
    "estimated_sales": 9.0,
    "amazon_link": "https://www.amazon.fr/gp/product/B0837B84W7/ref=xx_dp_cont_revecalc",
    "supplier_link": "https://www.qogita.com/products/6rxcb2265d/revox-for-women-30-ml/",
    "sas_link": "https://sas.selleramp.com/sas/lookup?SasLookup%5Bsearch_term%5D=B0837B84W7",
    "image_url": "https://m.media-amazon.com/images/I/41GJANTd7NL._SL120_.jpg",
    "posted": true,
    "posted_at": "2026-03-24T09:51:15.147197+00:00",
    "created_at": "2026-03-24T05:20:29.820307+00:00"
  },
  {
    "ean": "7046110060636",
    "asin": "B0BGS2DXWL",
    "name": "Green Clean Change Soft",
    "supplier_cost": 1.6320000000000001,
    "amazon_price": 8.27,
    "fees": 4.04,
    "profit": 2.5979999999999994,
    "roi": 159.19117647058818,
    "estimated_sales": 16.0,
    "amazon_link": "https://www.amazon.fr/gp/product/B0BGS2DXWL/ref=xx_dp_cont_revecalc",
    "supplier_link": "https://www.qogita.com/products/e7879ff5e12c4eac8d5aee3e291dbb54/jordan-tandem-toothbrush-green-clean-soft-brush-4-refills/",
    "sas_link": "https://sas.selleramp.com/sas/lookup?SasLookup%5Bsearch_term%5D=B0BGS2DXWL",
    "image_url": "https://m.media-amazon.com/images/I/31i1E54UueL._SL120_.jpg",
    "posted": true,
    "posted_at": "2026-03-24T09:51:45.041731+00:00",
    "created_at": "2026-03-24T05:20:29.851520+00:00"
  },
  {
    "ean": "9312657008027",
    "asin": "B01M9BRYDL",
    "name": "Jack N' Jill Kids Natural Toothpaste for Children, Made with Natural Ingredients, Helps with Tooth Decomposition and Fight Teeth, Suitable for Ages 6 Months and Above, No",
    "supplier_cost": 4.488,
    "amazon_price": 21.96,
    "fees": 8.94,
    "profit": 8.532,
    "roi": 190.10695187165774,
    "estimated_sales": 13.0,
    "amazon_link": "https://www.amazon.fr/gp/product/B01M9BRYDL/ref=xx_dp_cont_revecalc",
    "supplier_link": "https://www.qogita.com/products/39KNYmEn6x/jack-n-jill-natural-toothpaste-flavor-free/",
    "sas_link": "https://sas.selleramp.com/sas/lookup?SasLookup%5Bsearch_term%5D=B01M9BRYDL",
    "image_url": "https://m.media-amazon.com/images/I/31rNP+X1NJL._SL120_.jpg",
    "posted": true,
    "posted_at": "2026-03-24T09:52:12.136545+00:00",
    "created_at": "2026-03-24T05:20:29.866780+00:00"
  },
  {
    "ean": "5413975001548",
    "asin": "B07PVKTT6S",
    "name": "Cherry Stone Pillow - 100% Natural Organic Cotton Warm Cushion for Relaxing and Relieving Daily Aches, Muscle Pain, Cramps, Cervico Approx 13 x 54 cm",
    "supplier_cost": 9.36,
    "amazon_price": 24.42,
    "fees": 10.84,
    "profit": 4.220000000000002,
    "roi": 45.085470085470114,
    "estimated_sales": 100.0,
    "amazon_link": "https://www.amazon.fr/gp/product/B07PVKTT6S/ref=xx_dp_cont_revecalc",
    "supplier_link": "https://www.qogita.com/products/EujbcQrNe4/het-kersepitje-cherry-heat-pillow-cervico-13-x-55-cm/",
    "sas_link": "https://sas.selleramp.com/sas/lookup?SasLookup%5Bsearch_term%5D=B07PVKTT6S",
    "image_url": "https://m.media-amazon.com/images/I/413o0HsmDjL._SL120_.jpg",
    "posted": true,
    "posted_at": "2026-03-24T09:52:42.222120+00:00",
    "created_at": "2026-03-24T05:20:29.926908+00:00"
  },
  {
    "ean": "7317400015279",
    "asin": "B015D4MRZI",
    "name": "TePe 0.4mm Size 0 Original Interdental Brush - Pack of 8",
    "supplier_cost": 3.972,
    "amazon_price": 9.7,
    "fees": 4.14,
    "profit": 1.5879999999999996,
    "roi": 39.979859013091634,
    "estimated_sales": 2373.0,
    "amazon_link": "https://www.amazon.fr/gp/product/B015D4MRZI/ref=xx_dp_cont_revecalc",
    "supplier_link": "https://www.qogita.com/products/CxQmXuW7PF/tepe-interdental-brush-normal-04-mm-pink-8-pieces/",
    "sas_link": "https://sas.selleramp.com/sas/lookup?SasLookup%5Bsearch_term%5D=B015D4MRZI",
    "image_url": "https://m.media-amazon.com/images/I/41bfFiYlDSL._SL120_.jpg",
    "posted": true,
    "posted_at": "2026-03-24T09:53:02.323408+00:00",
    "created_at": "2026-03-24T05:20:30.004506+00:00"
  },
  {
    "ean": "8714789864006",
    "asin": "B0FF58TXRJ",
    "name": "ELMEX SENSITIVE PROFESS COLLUT (Pack of 2)",
    "supplier_cost": 4.992,
    "amazon_price": 19.64,
    "fees": 10.07,
    "profit": 4.578,
    "roi": 91.70673076923077,
    "estimated_sales": 7.0,
    "amazon_link": "https://www.amazon.fr/gp/product/B0FF58TXRJ/ref=xx_dp_cont_revecalc",
    "supplier_link": "https://www.qogita.com/products/4MYuQgUvwr/elmex-sensitivity-mouthwash-400ml-oral-care-solution/",
    "sas_link": "https://sas.selleramp.com/sas/lookup?SasLookup%5Bsearch_term%5D=B0FF58TXRJ",
    "image_url": "https://m.media-amazon.com/images/I/41mQaKVsG1L._SL120_.jpg",
    "posted": true,
    "posted_at": "2026-03-24T09:53:28.525114+00:00",
    "created_at": "2026-03-24T05:20:41.806673+00:00"
  },
  {
    "ean": "7630019900249",
    "asin": "B00GKOXWKK",
    "name": "Gum trav-ler 1312 scovol 0.6 x 4, Blue,White",
    "supplier_cost": 2.892,
    "amazon_price": 9.44,
    "fees": 4.11,
    "profit": 2.4379999999999993,
    "roi": 84.30152143845088,
    "estimated_sales": 200.0,
    "amazon_link": "https://www.amazon.fr/gp/product/B00GKOXWKK/ref=xx_dp_cont_revecalc",
    "supplier_link": "https://www.qogita.com/products/5P4eXR3f7t/eraser-travler-06-mm-4-pcs-brushes/",
    "sas_link": "https://sas.selleramp.com/sas/lookup?SasLookup%5Bsearch_term%5D=B00GKOXWKK",
    "image_url": "https://m.media-amazon.com/images/I/41QaNA2Mt6L._SL120_.jpg",
    "posted": true,
    "posted_at": "2026-03-24T09:53:53.960325+00:00",
    "created_at": "2026-03-24T05:20:42.850289+00:00"
  },
  {
    "ean": "7322540426335",
    "asin": "B003I60K9Y",
    "name": "TENA Men Level 1 f\u00fcr leichte Blasenschw\u00e4che, 12 pieces, 2er pack (2 x 12 stk)",
    "supplier_cost": 4.332,
    "amazon_price": 15.99,
    "fees": 8.79,
    "profit": 2.868000000000001,
    "roi": 66.20498614958453,
    "estimated_sales": 144.0,
    "amazon_link": "https://www.amazon.fr/gp/product/B003I60K9Y/ref=xx_dp_cont_revecalc",
    "supplier_link": "https://www.qogita.com/products/F6mS92yQmg/tena-mens-level-1-incontinence-pads/",
    "sas_link": "https://sas.selleramp.com/sas/lookup?SasLookup%5Bsearch_term%5D=B003I60K9Y",
    "image_url": "https://m.media-amazon.com/images/I/51HBiGMw1qL._SL120_.jpg",
    "posted": true,
    "posted_at": "2026-03-24T12:49:59.143317+00:00",
    "created_at": "2026-03-24T05:20:42.908839+00:00"
  },
  {
    "ean": "8032472034902",
    "asin": "B0FHQLW6Z1",
    "name": "Aboca Neobianacid Lemon Flavour 70 Tablets",
    "supplier_cost": 15.335999999999999,
    "amazon_price": 36.99,
    "fees": 11.62,
    "profit": 10.034000000000006,
    "roi": 65.42775169535737,
    "estimated_sales": 8.0,
    "amazon_link": "https://www.amazon.fr/gp/product/B0FHQLW6Z1/ref=xx_dp_cont_revecalc",
    "supplier_link": "https://www.qogita.com/products/fba7f162eccf439799a299bec4ed7f72/aboca-neobianacid-lemon-70-tablets-digestive-health-supplement/",
    "sas_link": "https://sas.selleramp.com/sas/lookup?SasLookup%5Bsearch_term%5D=B0FHQLW6Z1",
    "image_url": "https://m.media-amazon.com/images/I/41RTf-oSwQL._SL120_.jpg",
    "posted": true,
    "posted_at": "2026-03-24T12:50:18.956176+00:00",
    "created_at": "2026-03-24T05:20:47.894013+00:00"
  },
  {
    "ean": "9312657009017",
    "asin": "B0081ZPVIC",
    "name": "Jack N' Jill Natural Calendula Toothpaste Strawberry",
    "supplier_cost": 4.488,
    "amazon_price": 15.4,
    "fees": 7.93,
    "profit": 2.982,
    "roi": 66.44385026737967,
    "estimated_sales": 16.0,
    "amazon_link": "https://www.amazon.fr/gp/product/B0081ZPVIC/ref=xx_dp_cont_revecalc",
    "supplier_link": "https://www.qogita.com/products/FwSjo7uE5n/jack-n-jill-natural-toothpaste-strawberry-a-natural-toothpaste-for-kids/",
    "sas_link": "https://sas.selleramp.com/sas/lookup?SasLookup%5Bsearch_term%5D=B0081ZPVIC",
    "image_url": "https://m.media-amazon.com/images/I/41aJT+EzDiL._SL120_.jpg",
    "posted": true,
    "posted_at": "2026-03-24T12:50:45.894102+00:00",
    "created_at": "2026-03-24T05:20:52.222945+00:00"
  },
  {
    "ean": "8700216620710",
    "asin": "B0FXY5H2SX",
    "name": "Fixodent Plus Mordant Unbeatable Adhesive Cream for Total & Partial Denture 40gm (Pack of 4)",
    "supplier_cost": 2.664,
    "amazon_price": 19.58,
    "fees": 8.58,
    "profit": 8.335999999999999,
    "roi": 312.9129129129129,
    "estimated_sales": 2031.0,
    "amazon_link": "https://www.amazon.fr/gp/product/B0FXY5H2SX/ref=xx_dp_cont_revecalc",
    "supplier_link": "https://www.qogita.com/products/67071bb6b04d4e54b40bf3622bd40413/fixodent-adhesive-paste-plus-dual-power/",
    "sas_link": "https://sas.selleramp.com/sas/lookup?SasLookup%5Bsearch_term%5D=B0FXY5H2SX",
    "image_url": "https://m.media-amazon.com/images/I/41NNyJhx5pL._SL120_.jpg",
    "posted": true,
    "posted_at": "2026-03-24T12:51:14.773311+00:00",
    "created_at": "2026-03-24T05:20:52.303038+00:00"
  },
  {
    "ean": "0070942303460",
    "asin": "B0070X7ECC",
    "name": "Gum Proxabrush Trav-ler 4 Interdental Brushes 0.8 mm 1314",
    "supplier_cost": 2.892,
    "amazon_price": 8.2,
    "fees": 4.01,
    "profit": 1.2979999999999996,
    "roi": 44.88243430152142,
    "estimated_sales": 100.0,
    "amazon_link": "https://www.amazon.fr/gp/product/B0070X7ECC/ref=xx_dp_cont_revecalc",
    "supplier_link": "https://www.qogita.com/products/EJ6PPJukeq/eraser-trav-ler-fine-08-mm-4-pcs-brush/",
    "sas_link": "https://sas.selleramp.com/sas/lookup?SasLookup%5Bsearch_term%5D=B0070X7ECC",
    "image_url": "https://m.media-amazon.com/images/I/41Vgtk3+nyL._SL120_.jpg",
    "posted": true,
    "posted_at": "2026-03-24T12:51:44.764716+00:00",
    "created_at": "2026-03-24T05:20:52.307607+00:00"
  },
  {
    "ean": "7630019905855",
    "asin": "B0CLGYSMVP",
    "name": "GUM Soft-Picks Pro Medium Interdentalb\u00fcrsten, 30 pcs Interdental Brushes",
    "supplier_cost": 2.904,
    "amazon_price": 8.24,
    "fees": 4.04,
    "profit": 1.2960000000000003,
    "roi": 44.62809917355373,
    "estimated_sales": 50.0,
    "amazon_link": "https://www.amazon.fr/gp/product/B0CLGYSMVP/ref=xx_dp_cont_revecalc",
    "supplier_link": "https://www.qogita.com/products/faf1c346889d457a8ed3707ad84f8259/gum-soft-picks-pro-medium-690-interdental-cleaners-for-effective-oral-care/",
    "sas_link": "https://sas.selleramp.com/sas/lookup?SasLookup%5Bsearch_term%5D=B0CLGYSMVP",
    "image_url": "https://m.media-amazon.com/images/I/31UNXOotGLL._SL120_.jpg",
    "posted": true,
    "posted_at": "2026-03-24T12:52:02.760796+00:00",
    "created_at": "2026-03-24T05:20:52.313646+00:00"
  },
  {
    "ean": "4005900842893",
    "asin": "B0CLTTLVM3",
    "name": "HANSAPLAST Sensitive Hypo-Allergenic Dark Skin Dressings (1 x 20 Pieces) Breathable and Resistant Universal Dressings, Pre-Cut Dressings for Dark Skin (Pack of 2)",
    "supplier_cost": 1.752,
    "amazon_price": 6.98,
    "fees": 3.92,
    "profit": 1.3080000000000005,
    "roi": 74.65753424657538,
    "estimated_sales": 20.0,
    "amazon_link": "https://www.amazon.fr/gp/product/B0CLTTLVM3/ref=xx_dp_cont_revecalc",
    "supplier_link": "https://www.qogita.com/products/E6O54E/hansaplast-sensitive-dark/",
    "sas_link": "https://sas.selleramp.com/sas/lookup?SasLookup%5Bsearch_term%5D=B0CLTTLVM3",
    "image_url": "https://m.media-amazon.com/images/I/314jo-ooswL._SL120_.jpg",
    "posted": true,
    "posted_at": "2026-03-24T12:52:27.509695+00:00",
    "created_at": "2026-03-24T05:20:52.408121+00:00"
  },
  {
    "ean": "8720689036467",
    "asin": "B0DJQNLWGC",
    "name": "Philips Sonicare W2 Optimal White Original Replacement Toothbrush Heads, Black, Pack of 8, HX6068/88",
    "supplier_cost": 30.36,
    "amazon_price": 52.0,
    "fees": 13.94,
    "profit": 7.700000000000003,
    "roi": 25.362318840579718,
    "estimated_sales": 900.0,
    "amazon_link": "https://www.amazon.fr/gp/product/B0DJQNLWGC/ref=xx_dp_cont_revecalc",
    "supplier_link": "https://www.qogita.com/products/e27263aa0aa24ba3adc589a23603514e/philips-sonicare-w2-optimal-white-genuine-replacement-toothbrush-heads-black/",
    "sas_link": "https://sas.selleramp.com/sas/lookup?SasLookup%5Bsearch_term%5D=B0DJQNLWGC",
    "image_url": "https://m.media-amazon.com/images/I/51YGJ8WK4aL._SL120_.jpg",
    "posted": true,
    "posted_at": "2026-03-24T12:52:52.162449+00:00",
    "created_at": "2026-03-24T05:20:58.170423+00:00"
  },
  {
    "ean": "8427426012059",
    "asin": "B00ZR20ODY",
    "name": "Interprox plus mini conical red interdental brushes, Set of 3 to 6 pieces",
    "supplier_cost": 3.852,
    "amazon_price": 22.77,
    "fees": 9.06,
    "profit": 9.857999999999999,
    "roi": 255.91900311526476,
    "estimated_sales": 6.0,
    "amazon_link": "https://www.amazon.fr/gp/product/B00ZR20ODY/ref=xx_dp_cont_revecalc",
    "supplier_link": "https://www.qogita.com/products/GShR8zJ3t5/interprox-interprox-plus-1360-mini-conical-red/",
    "sas_link": "https://sas.selleramp.com/sas/lookup?SasLookup%5Bsearch_term%5D=B00ZR20ODY",
    "image_url": "https://m.media-amazon.com/images/I/51GFT36xHOL._SL120_.jpg",
    "posted": true,
    "posted_at": "2026-03-24T12:53:10.310686+00:00",
    "created_at": "2026-03-24T05:21:07.780288+00:00"
  },
  {
    "ean": "7630019900201",
    "asin": "B01122T0ZU",
    "name": "GUM TRAV-LER ISO 4 Interdental Brushes 1.3 mm Yellow 3 Packs of 6",
    "supplier_cost": 2.844,
    "amazon_price": 16.64,
    "fees": 8.11,
    "profit": 5.686000000000002,
    "roi": 199.92967651195505,
    "estimated_sales": 25.0,
    "amazon_link": "https://www.amazon.fr/gp/product/B01122T0ZU/ref=xx_dp_cont_revecalc",
    "supplier_link": "https://www.qogita.com/products/EZccerDGRN/cep-interdent-gum-travel-13-conical-1514/",
    "sas_link": "https://sas.selleramp.com/sas/lookup?SasLookup%5Bsearch_term%5D=B01122T0ZU",
    "image_url": "https://m.media-amazon.com/images/I/21fFws0a9AL._SL120_.jpg",
    "posted": true,
    "posted_at": "2026-03-24T12:53:35.721447+00:00",
    "created_at": "2026-03-24T05:21:07.827423+00:00"
  },
  {
    "ean": "7630019904797",
    "asin": "B09SLG7WFD",
    "name": "Gum sonic daily toothbrush refills white",
    "supplier_cost": 3.1559999999999997,
    "amazon_price": 9.95,
    "fees": 4.16,
    "profit": 2.6339999999999995,
    "roi": 83.46007604562736,
    "estimated_sales": 50.0,
    "amazon_link": "https://www.amazon.fr/gp/product/B09SLG7WFD/ref=xx_dp_cont_revecalc",
    "supplier_link": "https://www.qogita.com/products/5KVQWO/gum-sonic-daily-refills-white-brush-2-units/",
    "sas_link": "https://sas.selleramp.com/sas/lookup?SasLookup%5Bsearch_term%5D=B09SLG7WFD",
    "image_url": "https://m.media-amazon.com/images/I/31Sn2RVUIFL._SL120_.jpg",
    "posted": true,
    "posted_at": "2026-03-24T12:53:58.078290+00:00",
    "created_at": "2026-03-24T05:21:07.849335+00:00"
  },
  {
    "ean": "8056746070274",
    "asin": "B083M7JMLL",
    "name": "Curasept Periodontal Gel 0.5% 30ml",
    "supplier_cost": 3.9,
    "amazon_price": 13.96,
    "fees": 7.7,
    "profit": 2.3600000000000008,
    "roi": 60.51282051282053,
    "estimated_sales": 7.0,
    "amazon_link": "https://www.amazon.fr/gp/product/B083M7JMLL/ref=xx_dp_cont_revecalc",
    "supplier_link": "https://www.qogita.com/products/4ba67b084fc04a3d82b93891806b4c9d/curasept-ads-350-05-gel-30ml/",
    "sas_link": "https://sas.selleramp.com/sas/lookup?SasLookup%5Bsearch_term%5D=B083M7JMLL",
    "image_url": "https://m.media-amazon.com/images/I/31g9Du47YLL._SL120_.jpg",
    "posted": true,
    "posted_at": "2026-03-24T12:54:22.902910+00:00",
    "created_at": "2026-03-24T05:21:11.458653+00:00"
  },
  {
    "ean": "7317400009926",
    "asin": "B0041M5FAS",
    "name": "TePE Interdental Brushes, Extra Soft, Orange, 0.45mm/ISO 1, 8pcs, Effectively Removes Plaque Between Teeth, For Tight Spaces",
    "supplier_cost": 3.7079999999999997,
    "amazon_price": 8.99,
    "fees": 4.08,
    "profit": 1.2020000000000004,
    "roi": 32.41639697950379,
    "estimated_sales": 239.0,
    "amazon_link": "https://www.amazon.fr/gp/product/B0041M5FAS/ref=xx_dp_cont_revecalc",
    "supplier_link": "https://www.qogita.com/products/HY25mPiE9W/tepe-interdental-brush-extra-soft-045-mm-orange-8-pieces/",
    "sas_link": "https://sas.selleramp.com/sas/lookup?SasLookup%5Bsearch_term%5D=B0041M5FAS",
    "image_url": "https://m.media-amazon.com/images/I/41+7luWLZXL._SL120_.jpg",
    "posted": true,
    "posted_at": "2026-03-24T12:54:40.464505+00:00",
    "created_at": "2026-03-24T05:21:24.010223+00:00"
  },
  {
    "ean": "9312657010013",
    "asin": "B0081YVDM6",
    "name": "Jack N' Jill Natural Calendula Toothpaste Blueberry",
    "supplier_cost": 4.488,
    "amazon_price": 15.58,
    "fees": 7.96,
    "profit": 3.1319999999999997,
    "roi": 69.78609625668449,
    "estimated_sales": 11.0,
    "amazon_link": "https://www.amazon.fr/gp/product/B0081YVDM6/ref=xx_dp_cont_revecalc",
    "supplier_link": "https://www.qogita.com/products/HfUKyKiB8G/jack-n-jill-natural-toothpaste-blueberry/",
    "sas_link": "https://sas.selleramp.com/sas/lookup?SasLookup%5Bsearch_term%5D=B0081YVDM6",
    "image_url": "https://m.media-amazon.com/images/I/41aNvYmLrtL._SL120_.jpg",
    "posted": true,
    "posted_at": "2026-03-24T12:55:06.007544+00:00",
    "created_at": "2026-03-24T05:21:51.919082+00:00"
  },
  {
    "ean": "5901810006808",
    "asin": "B0CLM1PKTH",
    "name": "APIS ROSACEA-STOP Face Serum 100 ml with Soothing Agents, Reduces Redness, Relieves Inflammation, Reduces Skin Reactivity",
    "supplier_cost": 6.5280000000000005,
    "amazon_price": 18.85,
    "fees": 8.81,
    "profit": 3.5120000000000005,
    "roi": 53.799019607843135,
    "estimated_sales": 6.0,
    "amazon_link": "https://www.amazon.fr/gp/product/B0CLM1PKTH/ref=xx_dp_cont_revecalc",
    "supplier_link": "https://www.qogita.com/products/14WDKK/apis-rosacea-stop-redness-reducing-serum-100ml/",
    "sas_link": "https://sas.selleramp.com/sas/lookup?SasLookup%5Bsearch_term%5D=B0CLM1PKTH",
    "image_url": "https://m.media-amazon.com/images/I/312GQ-KV-wL._SL120_.jpg",
    "posted": true,
    "posted_at": "2026-03-24T12:55:32.431434+00:00",
    "created_at": "2026-03-24T05:21:52.275937+00:00"
  },
  {
    "ean": "8017331097311",
    "asin": "B0CYHBLDQX",
    "name": "Biorepair, Junior Toothpaste for Kids 6-12 Years, Fluoride Free, with Vitamin E, Antioxidant, Healthy Gums, Refreshing Mint Taste, 75ml",
    "supplier_cost": 2.34,
    "amazon_price": 12.99,
    "fees": 7.58,
    "profit": 3.0700000000000003,
    "roi": 131.1965811965812,
    "estimated_sales": 6.0,
    "amazon_link": "https://www.amazon.fr/gp/product/B0CYHBLDQX/ref=xx_dp_cont_revecalc",
    "supplier_link": "https://www.qogita.com/products/b02a814549a7489992271a3876e37f04/biorepair-junior-toothpaste-612-years-fluoridefree-with-vitamin-e-antioxidant-for-healthy-gums-refreshing-mint-flavor-75ml/",
    "sas_link": "https://sas.selleramp.com/sas/lookup?SasLookup%5Bsearch_term%5D=B0CYHBLDQX",
    "image_url": "https://m.media-amazon.com/images/I/41WpL2MCjxL._SL120_.jpg",
    "posted": true,
    "posted_at": "2026-03-24T12:55:53.681036+00:00",
    "created_at": "2026-03-24T05:21:52.302044+00:00"
  },
  {
    "ean": "7630019903011",
    "asin": "B014Q28MN4",
    "name": "Gum sensivital+ mouthwash 300 ml",
    "supplier_cost": 2.4,
    "amazon_price": 9.68,
    "fees": 6.27,
    "profit": 1.0100000000000002,
    "roi": 42.08333333333334,
    "estimated_sales": 12.0,
    "amazon_link": "https://www.amazon.fr/gp/product/B014Q28MN4/ref=xx_dp_cont_revecalc",
    "supplier_link": "https://www.qogita.com/products/A9G2yarcA8/gum-sensivital-mouthwash-for-sensitive-teeth/",
    "sas_link": "https://sas.selleramp.com/sas/lookup?SasLookup%5Bsearch_term%5D=B014Q28MN4",
    "image_url": "https://m.media-amazon.com/images/I/41Wsy+QIBWL._SL120_.jpg",
    "posted": true,
    "posted_at": "2026-03-24T12:56:16.838435+00:00",
    "created_at": "2026-03-24T05:21:53.100364+00:00"
  },
  {
    "ean": "0070942003087",
    "asin": "B00CQ8AW7U",
    "name": "GUM Single Tuft Toothbrush, Pack of 6 (6 Units)",
    "supplier_cost": 2.88,
    "amazon_price": 19.42,
    "fees": 7.49,
    "profit": 9.05,
    "roi": 314.23611111111114,
    "estimated_sales": 13.0,
    "amazon_link": "https://www.amazon.fr/gp/product/B00CQ8AW7U/ref=xx_dp_cont_revecalc",
    "supplier_link": "https://www.qogita.com/products/9HfuiJGFQw/eraser-single-tuft-toothbrush/",
    "sas_link": "https://sas.selleramp.com/sas/lookup?SasLookup%5Bsearch_term%5D=B00CQ8AW7U",
    "image_url": "https://m.media-amazon.com/images/I/21kWKGkOvzL._SL120_.jpg",
    "posted": true,
    "posted_at": "2026-03-24T12:56:32.005706+00:00",
    "created_at": "2026-03-24T05:22:06.587940+00:00"
  },
  {
    "ean": "7310610028718",
    "asin": "B08BZ6FRN5",
    "name": "Salvelox Pack of 20 Children's Patrol Bands, Soft, Durable, Breathable, Water and Sweat Resistant",
    "supplier_cost": 1.8119999999999998,
    "amazon_price": 9.42,
    "fees": 4.13,
    "profit": 3.478,
    "roi": 191.9426048565122,
    "estimated_sales": 23.0,
    "amazon_link": "https://www.amazon.fr/gp/product/B08BZ6FRN5/ref=xx_dp_cont_revecalc",
    "supplier_link": "https://www.qogita.com/products/ZD4NXY/salvelox-paw-patrol-plasters-20-units/",
    "sas_link": "https://sas.selleramp.com/sas/lookup?SasLookup%5Bsearch_term%5D=B08BZ6FRN5",
    "image_url": "https://m.media-amazon.com/images/I/51ed8z6lKmL._SL120_.jpg",
    "posted": true,
    "posted_at": "2026-03-24T12:57:01.123930+00:00",
    "created_at": "2026-03-24T05:22:19.975889+00:00"
  },
  {
    "ean": "8411883000131",
    "asin": "B07PFDH1BQ",
    "name": "Kesmar Ronquina Natural Herbs Hair Lotion (1000 ML)",
    "supplier_cost": 7.008,
    "amazon_price": 21.19,
    "fees": 10.53,
    "profit": 3.652000000000002,
    "roi": 52.111872146118756,
    "estimated_sales": 10.0,
    "amazon_link": "https://www.amazon.fr/gp/product/B07PFDH1BQ/ref=xx_dp_cont_revecalc",
    "supplier_link": "https://www.qogita.com/products/2P8WN8/ronquina-kesmar-1l/",
    "sas_link": "https://sas.selleramp.com/sas/lookup?SasLookup%5Bsearch_term%5D=B07PFDH1BQ",
    "image_url": "https://m.media-amazon.com/images/I/41mIXMMP0mL._SL120_.jpg",
    "posted": true,
    "posted_at": "2026-03-24T12:57:21.476703+00:00",
    "created_at": "2026-03-24T05:22:20.124902+00:00"
  },
  {
    "ean": "7317400010434",
    "asin": "B0CH3JKQ8D",
    "name": "TePe Mini X-Soft Small Toothbrush with Ultra Soft Filaments, Suitable for Ages 0-3, Pack of 3",
    "supplier_cost": 1.512,
    "amazon_price": 7.77,
    "fees": 4.01,
    "profit": 2.2479999999999998,
    "roi": 148.67724867724866,
    "estimated_sales": 80.0,
    "amazon_link": "https://www.amazon.fr/gp/product/B0CH3JKQ8D/ref=xx_dp_cont_revecalc",
    "supplier_link": "https://www.qogita.com/products/oDkw8aMgA8/tepe-mini-extra-soft-toothbrush-for-children-0-3-years/",
    "sas_link": "https://sas.selleramp.com/sas/lookup?SasLookup%5Bsearch_term%5D=B0CH3JKQ8D",
    "image_url": "https://m.media-amazon.com/images/I/412Yogy9eJL._SL120_.jpg",
    "posted": true,
    "posted_at": "2026-03-24T12:57:42.549072+00:00",
    "created_at": "2026-03-24T05:22:25.044317+00:00"
  },
  {
    "ean": "7630019900942",
    "asin": "B00D8XY2M8",
    "name": "GUM Soft-Picks Extra Large 40 pc. by Gum",
    "supplier_cost": 2.784,
    "amazon_price": 8.5,
    "fees": 4.03,
    "profit": 1.686,
    "roi": 60.560344827586206,
    "estimated_sales": 11.0,
    "amazon_link": "https://www.amazon.fr/gp/product/B00D8XY2M8/ref=xx_dp_cont_revecalc",
    "supplier_link": "https://www.qogita.com/products/8ArSvzW6q3/gum-sunstar-gum-gum-softpicks-original-xl-40-units/",
    "sas_link": "https://sas.selleramp.com/sas/lookup?SasLookup%5Bsearch_term%5D=B00D8XY2M8",
    "image_url": "https://m.media-amazon.com/images/I/41M1b-UoecL._SL120_.jpg",
    "posted": true,
    "posted_at": "2026-03-24T15:57:54.960048+00:00",
    "created_at": "2026-03-24T05:22:25.099695+00:00"
  },
  {
    "ean": "8427426011274",
    "asin": "B00ZRU5VWA",
    "name": "Interprox more Interdental brushes grey x-maxi 3 packs 4 pieces",
    "supplier_cost": 3.852,
    "amazon_price": 22.58,
    "fees": 9.05,
    "profit": 9.677999999999997,
    "roi": 251.24610591900307,
    "estimated_sales": 199.0,
    "amazon_link": "https://www.amazon.fr/gp/product/B00ZRU5VWA/ref=xx_dp_cont_revecalc",
    "supplier_link": "https://www.qogita.com/products/8nqTmC9dbo/interprox-dentaid-srl-interprox-plus-x-maxi-gray-4-pieces/",
    "sas_link": "https://sas.selleramp.com/sas/lookup?SasLookup%5Bsearch_term%5D=B00ZRU5VWA",
    "image_url": "https://m.media-amazon.com/images/I/41KwU8zcDYL._SL120_.jpg",
    "posted": true,
    "posted_at": "2026-03-24T15:58:17.191440+00:00",
    "created_at": "2026-03-24T05:22:40.976489+00:00"
  },
  {
    "ean": "4008233165745",
    "asin": "B0DZN2K55W",
    "name": "Kneipp Aromatic Muscle Relaxation Foam Bath - Additive with Precious Arnica Extract and Cabreuva Natural Essential Oils, Rosemary Pinus Heating Experience 400ml (Pack of 2)",
    "supplier_cost": 3.0119999999999996,
    "amazon_price": 14.02,
    "fees": 9.18,
    "profit": 1.8280000000000003,
    "roi": 60.69057104913681,
    "estimated_sales": 11.0,
    "amazon_link": "https://www.amazon.fr/gp/product/B0DZN2K55W/ref=xx_dp_cont_revecalc",
    "supplier_link": "https://www.qogita.com/products/6c168cbef6624d959418814f266be258/kneipp-bath-foam-for-muscles-and-joints-400-ml/",
    "sas_link": "https://sas.selleramp.com/sas/lookup?SasLookup%5Bsearch_term%5D=B0DZN2K55W",
    "image_url": "https://m.media-amazon.com/images/I/41jk4VbcCQL._SL120_.jpg",
    "posted": true,
    "posted_at": "2026-03-24T15:58:42.725921+00:00",
    "created_at": "2026-03-24T05:22:47.036017+00:00"
  },
  {
    "ean": "4002448039440",
    "asin": "B001PASC5E",
    "name": "Kukident Aktiv Plus Zahnersatz-Reinigungstabletten, 99 pc(s) Tablets",
    "supplier_cost": 3.6119999999999997,
    "amazon_price": 13.24,
    "fees": 7.62,
    "profit": 2.0080000000000005,
    "roi": 55.59246954595793,
    "estimated_sales": 6.0,
    "amazon_link": "https://www.amazon.fr/gp/product/B001PASC5E/ref=xx_dp_cont_revecalc",
    "supplier_link": "https://www.qogita.com/products/YRW4NW/kukident-kukident-active-plus-99-pieces/",
    "sas_link": "https://sas.selleramp.com/sas/lookup?SasLookup%5Bsearch_term%5D=B001PASC5E",
    "image_url": "https://m.media-amazon.com/images/I/41VrKMQ7SBL._SL120_.jpg",
    "posted": true,
    "posted_at": "2026-03-24T15:59:11.741603+00:00",
    "created_at": "2026-03-24T05:22:49.110783+00:00"
  },
  {
    "ean": "7610108021789",
    "asin": "B0C99VY2DP",
    "name": "Meridol Duo-Pack Soft Toothbrushes (Pack of 2)",
    "supplier_cost": 6.023999999999999,
    "amazon_price": 26.0,
    "fees": 8.46,
    "profit": 11.516,
    "roi": 191.16865869853922,
    "estimated_sales": 224.0,
    "amazon_link": "https://www.amazon.fr/gp/product/B0C99VY2DP/ref=xx_dp_cont_revecalc",
    "supplier_link": "https://www.qogita.com/products/63D7KK/meridol-toothbrush-gum-protection-gentle-double-pack-1-count/",
    "sas_link": "https://sas.selleramp.com/sas/lookup?SasLookup%5Bsearch_term%5D=B0C99VY2DP",
    "image_url": "https://m.media-amazon.com/images/I/419hRf0KCbL._SL120_.jpg",
    "posted": true,
    "posted_at": "2026-03-24T15:59:38.968475+00:00",
    "created_at": "2026-03-24T05:23:11.193796+00:00"
  },
  {
    "ean": "7317400014043",
    "asin": "B00DCVZ5K4",
    "name": "TePe Tartar Indicator Tablets Pack of 10 \u2013 Pack of 2",
    "supplier_cost": 2.28,
    "amazon_price": 10.2,
    "fees": 4.95,
    "profit": 2.9699999999999993,
    "roi": 130.26315789473682,
    "estimated_sales": 7.0,
    "amazon_link": "https://www.amazon.fr/gp/product/B00DCVZ5K4/ref=xx_dp_cont_revecalc",
    "supplier_link": "https://www.qogita.com/products/9vAwNqWyiA/tepe-plaqsearch/",
    "sas_link": "https://sas.selleramp.com/sas/lookup?SasLookup%5Bsearch_term%5D=B00DCVZ5K4",
    "image_url": "https://m.media-amazon.com/images/I/31KR8qaNE1L._SL120_.jpg",
    "posted": true,
    "posted_at": "2026-03-24T16:00:05.483098+00:00",
    "created_at": "2026-03-24T05:23:27.425200+00:00"
  },
  {
    "ean": "7317400016979",
    "asin": "B00FZURQZW",
    "name": "Tepe Original Interdental Brushes 0.5 mm Red 25 Pieces",
    "supplier_cost": 9.18,
    "amazon_price": 21.27,
    "fees": 7.17,
    "profit": 4.92,
    "roi": 53.59477124183007,
    "estimated_sales": 28.0,
    "amazon_link": "https://www.amazon.fr/gp/product/B00FZURQZW/ref=xx_dp_cont_revecalc",
    "supplier_link": "https://www.qogita.com/products/DPXO9K/tepe-original-interdental-brushes-05mm-red-25-brushes/",
    "sas_link": "https://sas.selleramp.com/sas/lookup?SasLookup%5Bsearch_term%5D=B00FZURQZW",
    "image_url": "https://m.media-amazon.com/images/I/41yOqiLkPML._SL120_.jpg",
    "posted": true,
    "posted_at": "2026-03-24T16:00:28.444858+00:00",
    "created_at": "2026-03-24T05:23:53.155187+00:00"
  },
  {
    "ean": "8430992120899",
    "asin": "B00J5FVKT6",
    "name": "THERMACARE ZONA LUMBAR CADERA 2 PARCHES",
    "supplier_cost": 8.267999999999999,
    "amazon_price": 20.39,
    "fees": 9.39,
    "profit": 2.732000000000001,
    "roi": 33.043057571359476,
    "estimated_sales": 12.0,
    "amazon_link": "https://www.amazon.fr/gp/product/B00J5FVKT6/ref=xx_dp_cont_revecalc",
    "supplier_link": "https://www.qogita.com/products/6Yz2GPhqqt/thermacare-thermacare-heatwraps-lower-back-and-hip-2-units/",
    "sas_link": "https://sas.selleramp.com/sas/lookup?SasLookup%5Bsearch_term%5D=B00J5FVKT6",
    "image_url": "https://m.media-amazon.com/images/I/41WZqcDxHxL._SL120_.jpg",
    "posted": true,
    "posted_at": "2026-03-24T16:00:54.900075+00:00",
    "created_at": "2026-03-24T05:23:58.358781+00:00"
  },
  {
    "ean": "4005800280689",
    "asin": "B08TMN3GJ4",
    "name": "Hansaplast Aqua Protect Waterproof Plasters with Extra Strong Adhesion, Ideal for Shower, Swimming and Bathing - Pack of 20",
    "supplier_cost": 2.448,
    "amazon_price": 7.46,
    "fees": 3.96,
    "profit": 1.052,
    "roi": 42.97385620915033,
    "estimated_sales": 17.0,
    "amazon_link": "https://www.amazon.fr/gp/product/B08TMN3GJ4/ref=xx_dp_cont_revecalc",
    "supplier_link": "https://www.qogita.com/products/9V9W1Y/hansaplast-hansaplast-aqua-protect-20-strips/",
    "sas_link": "https://sas.selleramp.com/sas/lookup?SasLookup%5Bsearch_term%5D=B08TMN3GJ4",
    "image_url": "https://m.media-amazon.com/images/I/41FOVEVscNL._SL120_.jpg",
    "posted": true,
    "posted_at": "2026-03-24T16:01:14.509690+00:00",
    "created_at": "2026-03-24T05:23:58.433944+00:00"
  },
  {
    "ean": "4005800486005",
    "asin": "B000TGIGLU",
    "name": "Hansaplast H\u00fchneraugenringe 20 Pieces",
    "supplier_cost": 2.76,
    "amazon_price": 7.99,
    "fees": 3.75,
    "profit": 1.4800000000000004,
    "roi": 53.623188405797116,
    "estimated_sales": 5.0,
    "amazon_link": "https://www.amazon.fr/gp/product/B000TGIGLU/ref=xx_dp_cont_revecalc",
    "supplier_link": "https://www.qogita.com/products/YmUin9vEij/hansaplast-hansaplast-corn-patch-band-aid-20-pieces/",
    "sas_link": "https://sas.selleramp.com/sas/lookup?SasLookup%5Bsearch_term%5D=B000TGIGLU",
    "image_url": "https://m.media-amazon.com/images/I/41+g+wAZBHL._SL120_.jpg",
    "posted": true,
    "posted_at": "2026-03-24T16:01:44.113283+00:00",
    "created_at": "2026-03-24T05:23:58.517836+00:00"
  },
  {
    "ean": "8427426006300",
    "asin": "B00ZPF16M6",
    "name": "Interprox Plus Super Micro Interdental Brushes Orange Pack of 6 (3 x 6 pieces)",
    "supplier_cost": 3.852,
    "amazon_price": 23.79,
    "fees": 9.24,
    "profit": 10.697999999999999,
    "roi": 277.7258566978193,
    "estimated_sales": 200.0,
    "amazon_link": "https://www.amazon.fr/gp/product/B00ZPF16M6/ref=xx_dp_cont_revecalc",
    "supplier_link": "https://www.qogita.com/products/GxdkkpVPXP/interprox-dentaid-srl-interprox-plus-supermicro-orange-1460-6-pieces/",
    "sas_link": "https://sas.selleramp.com/sas/lookup?SasLookup%5Bsearch_term%5D=B00ZPF16M6",
    "image_url": "https://m.media-amazon.com/images/I/419dmP0nMAL._SL120_.jpg",
    "posted": true,
    "posted_at": "2026-03-24T16:01:59.640217+00:00",
    "created_at": "2026-03-24T05:24:02.713944+00:00"
  },
  {
    "ean": "8718951442153",
    "asin": "B09SVS3VCF",
    "name": "elmex Bambus-Zahnh\u00f6lzer mit Minzgeschmack, 96 pcs. Teeth wood",
    "supplier_cost": 2.832,
    "amazon_price": 8.75,
    "fees": 4.08,
    "profit": 1.838,
    "roi": 64.90112994350284,
    "estimated_sales": 18.0,
    "amazon_link": "https://www.amazon.fr/gp/product/B09SVS3VCF/ref=xx_dp_cont_revecalc",
    "supplier_link": "https://www.qogita.com/products/N87RLO/elmex-dental-sticks-96-pieces-mint-flavored-bamboo-dental-sticks/",
    "sas_link": "https://sas.selleramp.com/sas/lookup?SasLookup%5Bsearch_term%5D=B09SVS3VCF",
    "image_url": "https://m.media-amazon.com/images/I/41Ehp5jUDqL._SL120_.jpg",
    "posted": true,
    "posted_at": "2026-03-24T16:02:15.623633+00:00",
    "created_at": "2026-03-24T05:24:02.756369+00:00"
  },
  {
    "ean": "8901030741203",
    "asin": "B08X8MY3KY",
    "name": "vaseline Pet Jelly 450g",
    "supplier_cost": 5.712,
    "amazon_price": 17.66,
    "fees": 9.75,
    "profit": 2.1980000000000004,
    "roi": 38.480392156862756,
    "estimated_sales": 5.0,
    "amazon_link": "https://www.amazon.fr/gp/product/B08X8MY3KY/ref=xx_dp_cont_revecalc",
    "supplier_link": "https://www.qogita.com/products/GFqLkUAzCD/vaseline-original-protecting-jelly-dermatologist-tested-skin-protectant-450ml/",
    "sas_link": "https://sas.selleramp.com/sas/lookup?SasLookup%5Bsearch_term%5D=B08X8MY3KY",
    "image_url": "https://m.media-amazon.com/images/I/31nFuWdMIGL._SL120_.jpg",
    "posted": true,
    "posted_at": "2026-03-24T16:02:30.988712+00:00",
    "created_at": "2026-03-24T05:24:02.827429+00:00"
  },
  {
    "ean": "8412428011162",
    "asin": "B01IQT4BII",
    "name": "Cuidado Bucal Infantil The Paw Patrol Cartoon Set (4 pcs)",
    "supplier_cost": 5.207999999999999,
    "amazon_price": 15.99,
    "fees": 8.78,
    "profit": 2.0020000000000016,
    "roi": 38.440860215053796,
    "estimated_sales": 7.0,
    "amazon_link": "https://www.amazon.fr/gp/product/B01IQT4BII/ref=xx_dp_cont_revecalc",
    "supplier_link": "https://www.qogita.com/products/JR3vypP6DL/nickelodeon-paw-patrol-toothbrush-set-4-pieces/",
    "sas_link": "https://sas.selleramp.com/sas/lookup?SasLookup%5Bsearch_term%5D=B01IQT4BII",
    "image_url": "https://m.media-amazon.com/images/I/51Wz8sdX7yL._SL120_.jpg",
    "posted": true,
    "posted_at": "2026-03-24T16:02:56.550567+00:00",
    "created_at": "2026-03-24T05:24:04.542242+00:00"
  },
  {
    "ean": "4005900405104",
    "asin": "B07NW5K7Y5",
    "name": "HANSAPLAST Universal Round Dressings - 50 Units",
    "supplier_cost": 2.5559999999999996,
    "amazon_price": 18.32,
    "fees": 8.39,
    "profit": 7.3740000000000006,
    "roi": 288.4976525821597,
    "estimated_sales": 10.0,
    "amazon_link": "https://www.amazon.fr/gp/product/B07NW5K7Y5/ref=xx_dp_cont_revecalc",
    "supplier_link": "https://www.qogita.com/products/8378a4e189464ef38235abeca613e472/hansaplast-universal-round-dressings-50-units/",
    "sas_link": "https://sas.selleramp.com/sas/lookup?SasLookup%5Bsearch_term%5D=B07NW5K7Y5",
    "image_url": "https://m.media-amazon.com/images/I/41zWfqk5hjS._SL120_.jpg",
    "posted": true,
    "posted_at": "2026-03-24T16:03:17.282957+00:00",
    "created_at": "2026-03-24T05:24:07.734036+00:00"
  },
  {
    "ean": "8901571011018",
    "asin": "B0CHFT9CY2",
    "name": "Sensodyne Pack of 6 toothbrushes sensitive, soft (colour may vary)",
    "supplier_cost": 1.536,
    "amazon_price": 16.96,
    "fees": 8.22,
    "profit": 7.204000000000001,
    "roi": 469.0104166666667,
    "estimated_sales": 6.0,
    "amazon_link": "https://www.amazon.fr/gp/product/B0CHFT9CY2/ref=xx_dp_cont_revecalc",
    "supplier_link": "https://www.qogita.com/products/93DZ11/sensodyne-toothbrush-sensitive-soft-assorted-3-count/",
    "sas_link": "https://sas.selleramp.com/sas/lookup?SasLookup%5Bsearch_term%5D=B0CHFT9CY2",
    "image_url": "https://m.media-amazon.com/images/I/51jSDhdwfQL._SL120_.jpg",
    "posted": true,
    "posted_at": "2026-03-24T16:03:41.226043+00:00",
    "created_at": "2026-03-24T05:24:09.154762+00:00"
  },
  {
    "ean": "4068881000188",
    "asin": "B00X9VRF9Q",
    "name": "Denivit toothpaste stain remover 50 ml",
    "supplier_cost": 1.74,
    "amazon_price": 9.46,
    "fees": 5.89,
    "profit": 1.8300000000000012,
    "roi": 105.17241379310352,
    "estimated_sales": 10.0,
    "amazon_link": "https://www.amazon.fr/gp/product/B00X9VRF9Q/ref=xx_dp_cont_revecalc",
    "supplier_link": "https://www.qogita.com/products/6f10a53bb57d42f0a31922fc9973dfa9/denivit-whitening-anti-stain-intense-toothpaste-50-ml/",
    "sas_link": "https://sas.selleramp.com/sas/lookup?SasLookup%5Bsearch_term%5D=B00X9VRF9Q",
    "image_url": "https://m.media-amazon.com/images/I/516H2oo52dL._SL120_.jpg",
    "posted": true,
    "posted_at": "2026-03-24T16:04:01.618010+00:00",
    "created_at": "2026-03-24T05:24:22.250676+00:00"
  },
  {
    "ean": "8032472006664",
    "asin": "B00WIBM3TK",
    "name": "ABOCA Neobianacid Reflujo 45 Comp \u2013 easy to integrate into the daily routine, box of 45 tablets, easy to integrate into the daily routine and becomes a reliable ally in",
    "supplier_cost": 13.392,
    "amazon_price": 26.95,
    "fees": 10.06,
    "profit": 3.498000000000001,
    "roi": 26.120071684587824,
    "estimated_sales": 5.0,
    "amazon_link": "https://www.amazon.fr/gp/product/B00WIBM3TK/ref=xx_dp_cont_revecalc",
    "supplier_link": "https://www.qogita.com/products/qXvzBKCbVr/aboca-neobianacid-heartburn-reflux-tablets/",
    "sas_link": "https://sas.selleramp.com/sas/lookup?SasLookup%5Bsearch_term%5D=B00WIBM3TK",
    "image_url": "https://m.media-amazon.com/images/I/31eaKEJEg+L._SL120_.jpg",
    "posted": true,
    "posted_at": "2026-03-24T16:04:24.082935+00:00",
    "created_at": "2026-03-24T05:24:22.276558+00:00"
  },
  {
    "ean": "8017331054215",
    "asin": "B01N4RDDBQ",
    "name": "Biorepair: Pro White Whitening Toothpaste with MicroRepair - 2.5 Fluid Ounce (75ml) - 2 Tubes",
    "supplier_cost": 3.0599999999999996,
    "amazon_price": 16.98,
    "fees": 8.2,
    "profit": 5.7200000000000015,
    "roi": 186.92810457516347,
    "estimated_sales": 12.0,
    "amazon_link": "https://www.amazon.fr/gp/product/B01N4RDDBQ/ref=xx_dp_cont_revecalc",
    "supplier_link": "https://www.qogita.com/products/7V5E28/biorepair-for-white-toothpaste-whitening-toothpaste/",
    "sas_link": "https://sas.selleramp.com/sas/lookup?SasLookup%5Bsearch_term%5D=B01N4RDDBQ",
    "image_url": "https://m.media-amazon.com/images/I/51A3qb-UDaL._SL120_.jpg",
    "posted": true,
    "posted_at": "2026-03-24T16:04:52.835246+00:00",
    "created_at": "2026-03-24T05:24:31.043950+00:00"
  },
  {
    "ean": "5022496016919",
    "asin": "B0C9QYVQTT",
    "name": "Dabur Organic Toothpaste Neem 100ml - Organic Protection, Strengthens Gums, Anti-Plaque, Neem & Lotur Freshness",
    "supplier_cost": 2.796,
    "amazon_price": 9.99,
    "fees": 5.94,
    "profit": 1.254,
    "roi": 44.84978540772532,
    "estimated_sales": 7.0,
    "amazon_link": "https://www.amazon.fr/gp/product/B0C9QYVQTT/ref=xx_dp_cont_revecalc",
    "supplier_link": "https://www.qogita.com/products/3cf379962c364ecbbad0e92ca7bd6edb/dabur-antibacterial-neem-toothpaste-100ml-natural-oral-care-with-neem-extracts-for-fresh-breath-and-healthy-teeth-fluoride-free-formula/",
    "sas_link": "https://sas.selleramp.com/sas/lookup?SasLookup%5Bsearch_term%5D=B0C9QYVQTT",
    "image_url": "https://m.media-amazon.com/images/I/414QqJyiB7L._SL120_.jpg",
    "posted": true,
    "posted_at": "2026-03-24T16:05:20.215678+00:00",
    "created_at": "2026-03-24T05:24:31.050595+00:00"
  },
  {
    "ean": "5901810000103",
    "asin": "B08FCFNYT7",
    "name": "APIS COUPEROSE-STOP Vitamin Cream for Sensitive Skin with Couperose Problems with Vitamin C, Ginko, Ceramides and Hyaluronic Acid | Relieves",
    "supplier_cost": 9.12,
    "amazon_price": 21.48,
    "fees": 9.22,
    "profit": 3.1400000000000006,
    "roi": 34.429824561403514,
    "estimated_sales": 9.0,
    "amazon_link": "https://www.amazon.fr/gp/product/B08FCFNYT7/ref=xx_dp_cont_revecalc",
    "supplier_link": "https://www.qogita.com/products/DZQNK4/apis-couperose-stop-vitamin-cream-for-sensitive-skin-with-enlarged-capillaries-100ml/",
    "sas_link": "https://sas.selleramp.com/sas/lookup?SasLookup%5Bsearch_term%5D=B08FCFNYT7",
    "image_url": "https://m.media-amazon.com/images/I/31jEDtkwAbL._SL120_.jpg",
    "posted": true,
    "posted_at": "2026-03-24T16:05:37.669805+00:00",
    "created_at": "2026-03-24T05:24:35.654485+00:00"
  },
  {
    "ean": "0070942018555",
    "asin": "B002WZHT8M",
    "name": "GUM butlerweave 1855 wax floss mint 55m",
    "supplier_cost": 1.344,
    "amazon_price": 8.89,
    "fees": 5.85,
    "profit": 1.6960000000000008,
    "roi": 126.19047619047625,
    "estimated_sales": 5.0,
    "amazon_link": "https://www.amazon.fr/gp/product/B002WZHT8M/ref=xx_dp_cont_revecalc",
    "supplier_link": "https://www.qogita.com/products/88f7DsDvZB/seda-dent-gum-with-cera-ment-flavor/",
    "sas_link": "https://sas.selleramp.com/sas/lookup?SasLookup%5Bsearch_term%5D=B002WZHT8M",
    "image_url": "https://m.media-amazon.com/images/I/41j5BP-EMtL._SL120_.jpg",
    "posted": true,
    "posted_at": "2026-03-24T18:50:50.339086+00:00",
    "created_at": "2026-03-24T05:24:35.733907+00:00"
  },
  {
    "ean": "7317400016931",
    "asin": "B0C2RK98GV",
    "name": "TEPE 25 Pcs Interdental Brush Soft Teeth Cleaning Brush 1.3mm Grey Size 7",
    "supplier_cost": 9.18,
    "amazon_price": 19.67,
    "fees": 6.92,
    "profit": 3.570000000000002,
    "roi": 38.888888888888914,
    "estimated_sales": 5.0,
    "amazon_link": "https://www.amazon.fr/gp/product/B0C2RK98GV/ref=xx_dp_cont_revecalc",
    "supplier_link": "https://www.qogita.com/products/QE8N28/tepe-original-interdental-brushes-gray-13mm-25-pieces/",
    "sas_link": "https://sas.selleramp.com/sas/lookup?SasLookup%5Bsearch_term%5D=B0C2RK98GV",
    "image_url": "https://m.media-amazon.com/images/I/41f8HDC8e6L._SL120_.jpg",
    "posted": true,
    "posted_at": "2026-03-24T18:51:16.946270+00:00",
    "created_at": "2026-03-24T05:24:39.843182+00:00"
  },
  {
    "ean": "3574661581019",
    "asin": "B0CZF9F9ZX",
    "name": "Neutrogena Cica Balm Body and Face Cream with Vegetable Glycerin, Intense Repair for Damaged Skin, 100 ml (Pack of 2)",
    "supplier_cost": 7.284,
    "amazon_price": 22.8,
    "fees": 9.42,
    "profit": 6.096000000000001,
    "roi": 83.69028006589787,
    "estimated_sales": 7.0,
    "amazon_link": "https://www.amazon.fr/gp/product/B0CZF9F9ZX/ref=xx_dp_cont_revecalc",
    "supplier_link": "https://www.qogita.com/products/55858b3563e64ba4a355cf898a32ba7a/neutrogena-intense-repair-cica-balm-100ml/",
    "sas_link": "https://sas.selleramp.com/sas/lookup?SasLookup%5Bsearch_term%5D=B0CZF9F9ZX",
    "image_url": "https://m.media-amazon.com/images/I/5148+zFykEL._SL120_.jpg",
    "posted": true,
    "posted_at": "2026-03-24T18:51:41.181687+00:00",
    "created_at": "2026-03-24T05:24:39.873179+00:00"
  },
  {
    "ean": "8470001571694",
    "asin": "B00BN7XMFY",
    "name": "ORALDINE Antiseptic Mouthwash (200 ml)",
    "supplier_cost": 3.36,
    "amazon_price": 13.99,
    "fees": 8.43,
    "profit": 2.2000000000000006,
    "roi": 65.4761904761905,
    "estimated_sales": 13.0,
    "amazon_link": "https://www.amazon.fr/gp/product/B00BN7XMFY/ref=xx_dp_cont_revecalc",
    "supplier_link": "https://www.qogita.com/products/VWO5DR/oraldine-oraldine-oral-antiseptic-200ml/",
    "sas_link": "https://sas.selleramp.com/sas/lookup?SasLookup%5Bsearch_term%5D=B00BN7XMFY",
    "image_url": "https://m.media-amazon.com/images/I/31K6CVpS5eL._SL120_.jpg",
    "posted": true,
    "posted_at": "2026-03-24T18:52:04.663869+00:00",
    "created_at": "2026-03-24T05:24:44.407599+00:00"
  },
  {
    "ean": "7610108047536",
    "asin": "B01HYJL242",
    "name": "Elmex SENSITIVE PROFESSIONAL Toothpaste with DNA PRO, Pack Of 3 (3 x 75 ml)",
    "supplier_cost": 5.388,
    "amazon_price": 22.99,
    "fees": 9.49,
    "profit": 8.111999999999998,
    "roi": 150.5567928730512,
    "estimated_sales": 15.0,
    "amazon_link": "https://www.amazon.fr/gp/product/B01HYJL242/ref=xx_dp_cont_revecalc",
    "supplier_link": "https://www.qogita.com/products/OWZZE9/elmex-sensitive-professional-medicated-toothpaste-75-ml-toothpaste-1x75ml/",
    "sas_link": "https://sas.selleramp.com/sas/lookup?SasLookup%5Bsearch_term%5D=B01HYJL242",
    "image_url": "https://m.media-amazon.com/images/I/41iBoEg7pIL._SL120_.jpg",
    "posted": true,
    "posted_at": "2026-03-24T18:52:34.418665+00:00",
    "created_at": "2026-03-24T05:24:52.776226+00:00"
  },
  {
    "ean": "8718951052109",
    "asin": "B07575QTJ7",
    "name": "Colgate Minions Kids Extra Soft Battery Toothbrush 3+ Years (Assorted Colour)",
    "supplier_cost": 4.944,
    "amazon_price": 13.07,
    "fees": 6.46,
    "profit": 1.6660000000000004,
    "roi": 33.697411003236255,
    "estimated_sales": 7.0,
    "amazon_link": "https://www.amazon.fr/gp/product/B07575QTJ7/ref=xx_dp_cont_revecalc",
    "supplier_link": "https://www.qogita.com/products/7GULrPE296/colgate-minions-kids-electric-childrens-toothbrush-on-battery/",
    "sas_link": "https://sas.selleramp.com/sas/lookup?SasLookup%5Bsearch_term%5D=B07575QTJ7",
    "image_url": "https://m.media-amazon.com/images/I/31XRAXh+gqL._SL120_.jpg",
    "posted": true,
    "posted_at": "2026-03-24T18:52:55.367946+00:00",
    "created_at": "2026-03-24T05:25:02.706595+00:00"
  },
  {
    "ean": "3574661731001",
    "asin": "B0C3DBHTSJ",
    "name": "LISTERINE Mundsp\u00fclung Total Care Zahn-Schutz f\u00fcr starke z\u00e4hne, 500 ml Solution",
    "supplier_cost": 4.032,
    "amazon_price": 17.07,
    "fees": 8.66,
    "profit": 4.378,
    "roi": 108.58134920634922,
    "estimated_sales": 93.0,
    "amazon_link": "https://www.amazon.fr/gp/product/B0C3DBHTSJ/ref=xx_dp_cont_revecalc",
    "supplier_link": "https://www.qogita.com/products/c997c747ee8049fcb6fef45f59864af2/listerine-total-care-tooth-protection-500ml/",
    "sas_link": "https://sas.selleramp.com/sas/lookup?SasLookup%5Bsearch_term%5D=B0C3DBHTSJ",
    "image_url": "https://m.media-amazon.com/images/I/41ChNhfSIxL._SL120_.jpg",
    "posted": true,
    "posted_at": "2026-03-24T18:53:15.671812+00:00",
    "created_at": "2026-03-24T05:25:13.370413+00:00"
  },
  {
    "ean": "4009932002164",
    "asin": "B01GIF83J0",
    "name": "Protefix Extra Strong Denture Fixing Cream Neutral 3x47g",
    "supplier_cost": 2.376,
    "amazon_price": 16.69,
    "fees": 8.14,
    "profit": 6.174000000000001,
    "roi": 259.84848484848493,
    "estimated_sales": 5.0,
    "amazon_link": "https://www.amazon.fr/gp/product/B01GIF83J0/ref=xx_dp_cont_revecalc",
    "supplier_link": "https://www.qogita.com/products/3889dffe059d47fe97e55ff9ff675b1d/protefix-protefix-dental-adhesive-cream-47g-neutral/",
    "sas_link": "https://sas.selleramp.com/sas/lookup?SasLookup%5Bsearch_term%5D=B01GIF83J0",
    "image_url": "https://m.media-amazon.com/images/I/61I57WcjMdL._SL120_.jpg",
    "posted": true,
    "posted_at": "2026-03-24T18:53:31.909311+00:00",
    "created_at": "2026-03-24T05:25:17.464820+00:00"
  },
  {
    "ean": "8000036024591",
    "asin": "B01N6YJYKG",
    "name": "ThermaCare Neck Shoulder Self-Warming 6 Cuffs",
    "supplier_cost": 14.52,
    "amazon_price": 29.9,
    "fees": 10.94,
    "profit": 4.440000000000001,
    "roi": 30.578512396694222,
    "estimated_sales": 26.0,
    "amazon_link": "https://www.amazon.fr/gp/product/B01N6YJYKG/ref=xx_dp_cont_revecalc",
    "supplier_link": "https://www.qogita.com/products/27feae57d5ee4567ae8902414b3a175c/angelini-thermacare-selfheating-patches-for-neck-shoulder-and-wrist-6-disposable-patches/",
    "sas_link": "https://sas.selleramp.com/sas/lookup?SasLookup%5Bsearch_term%5D=B01N6YJYKG",
    "image_url": "https://m.media-amazon.com/images/I/41q52YYFUnL._SL120_.jpg",
    "posted": true,
    "posted_at": "2026-03-24T18:53:52.390755+00:00",
    "created_at": "2026-03-24T05:25:17.471424+00:00"
  },
  {
    "ean": "8714789086477",
    "asin": "B0012RXQD8",
    "name": "Colgate Extra soft toothbrush, children ages 3 to 5, various colours and models",
    "supplier_cost": 0.732,
    "amazon_price": 5.67,
    "fees": 3.8,
    "profit": 1.1380000000000001,
    "roi": 155.46448087431696,
    "estimated_sales": 17.0,
    "amazon_link": "https://www.amazon.fr/gp/product/B0012RXQD8/ref=xx_dp_cont_revecalc",
    "supplier_link": "https://www.qogita.com/products/BXZU6AYmuE/12-x-colgate-smiles-toothbrush-ages-2-6/",
    "sas_link": "https://sas.selleramp.com/sas/lookup?SasLookup%5Bsearch_term%5D=B0012RXQD8",
    "image_url": "https://m.media-amazon.com/images/I/41WzJitP+iL._SL120_.jpg",
    "posted": true,
    "posted_at": "2026-03-24T18:54:13.048270+00:00",
    "created_at": "2026-03-24T05:25:17.510298+00:00"
  },
  {
    "ean": "5029053579504",
    "asin": "B09K7LC4V3",
    "name": "KLEENEX - Handkerchiefs Balsam box (24 boxes of 64 tissues) - deposits a protective balm that soothes your noses ideal in case of severe colds - Made in France",
    "supplier_cost": 1.38,
    "amazon_price": 45.36,
    "fees": 18.24,
    "profit": 25.740000000000002,
    "roi": 1865.217391304348,
    "estimated_sales": 100.0,
    "amazon_link": "https://www.amazon.fr/gp/product/B09K7LC4V3/ref=xx_dp_cont_revecalc",
    "supplier_link": "https://www.qogita.com/products/KXNO77/kleenex-balsam-tissues/",
    "sas_link": "https://sas.selleramp.com/sas/lookup?SasLookup%5Bsearch_term%5D=B09K7LC4V3",
    "image_url": "https://m.media-amazon.com/images/I/51VnU6lx+lL._SL120_.jpg",
    "posted": true,
    "posted_at": "2026-03-24T18:54:37.959896+00:00",
    "created_at": "2026-03-24T05:25:22.952325+00:00"
  },
  {
    "ean": "4009932002201",
    "asin": "B0013BCKSU",
    "name": "Protefix 30 x White Natriumalginat Upper Jaw Denture Pads",
    "supplier_cost": 2.7119999999999997,
    "amazon_price": 7.78,
    "fees": 4.0,
    "profit": 1.0680000000000005,
    "roi": 39.38053097345135,
    "estimated_sales": 12.0,
    "amazon_link": "https://www.amazon.fr/gp/product/B0013BCKSU/ref=xx_dp_cont_revecalc",
    "supplier_link": "https://www.qogita.com/products/922bf751fbaa4f098bd023c900b320e0/protefix-denture-pad-for-upper-jaw/",
    "sas_link": "https://sas.selleramp.com/sas/lookup?SasLookup%5Bsearch_term%5D=B0013BCKSU",
    "image_url": "https://m.media-amazon.com/images/I/51JAYCgm09L._SL120_.jpg",
    "posted": true,
    "posted_at": "2026-03-24T18:54:55.426797+00:00",
    "created_at": "2026-03-24T05:25:27.767570+00:00"
  },
  {
    "ean": "5054563925381",
    "asin": "B00OY3FBQW",
    "name": "Dr.BEST Soft interdental toothbrush (1 piece) for deep cleaning of interdental spaces",
    "supplier_cost": 2.52,
    "amazon_price": 11.49,
    "fees": 5.11,
    "profit": 3.86,
    "roi": 153.17460317460316,
    "estimated_sales": 7.0,
    "amazon_link": "https://www.amazon.fr/gp/product/B00OY3FBQW/ref=xx_dp_cont_revecalc",
    "supplier_link": "https://www.qogita.com/products/O73E50/dr-best-interdental-toothbrush-soft-for-thorough-cleaning-between-teeth-with/",
    "sas_link": "https://sas.selleramp.com/sas/lookup?SasLookup%5Bsearch_term%5D=B00OY3FBQW",
    "image_url": "https://m.media-amazon.com/images/I/41jQjFsOewL._SL120_.jpg",
    "posted": true,
    "posted_at": "2026-03-24T18:55:12.860682+00:00",
    "created_at": "2026-03-24T05:25:46.082654+00:00"
  },
  {
    "ean": "5054563209290",
    "asin": "B0D66WFNLT",
    "name": "Sensodyne ProSchmelz Daily Fluoride Repair Toothpaste 1 x 75 ml Repairs Acid Weakened Teeth Enamel",
    "supplier_cost": 4.584,
    "amazon_price": 16.53,
    "fees": 8.11,
    "profit": 3.836000000000002,
    "roi": 83.68237347294945,
    "estimated_sales": 5.0,
    "amazon_link": "https://www.amazon.fr/gp/product/B0D66WFNLT/ref=xx_dp_cont_revecalc",
    "supplier_link": "https://www.qogita.com/products/8c557e576b964a8fb066a29cf92922d4/sensodyne-proschmelz-repair-toothpaste-daily-toothpaste-with-fluoride-75ml/",
    "sas_link": "https://sas.selleramp.com/sas/lookup?SasLookup%5Bsearch_term%5D=B0D66WFNLT",
    "image_url": "https://m.media-amazon.com/images/I/31tPrR2uTCL._SL120_.jpg",
    "posted": true,
    "posted_at": "2026-03-24T18:55:33.713056+00:00",
    "created_at": "2026-03-24T05:25:46.108612+00:00"
  },
  {
    "ean": "8427426011281",
    "asin": "B00ZRVERRY",
    "name": "Interprox Interdental brushes black XX-maxi pack, Pack of 3 to 4 pieces",
    "supplier_cost": 3.924,
    "amazon_price": 23.55,
    "fees": 9.17,
    "profit": 10.456000000000001,
    "roi": 266.4627930682977,
    "estimated_sales": 201.0,
    "amazon_link": "https://www.amazon.fr/gp/product/B00ZRVERRY/ref=xx_dp_cont_revecalc",
    "supplier_link": "https://www.qogita.com/products/JL4oCzQ5GC/dentaid-srl-interprox-interprox-plus-xx-maxi-6-pieces/",
    "sas_link": "https://sas.selleramp.com/sas/lookup?SasLookup%5Bsearch_term%5D=B00ZRVERRY",
    "image_url": "https://m.media-amazon.com/images/I/416Oxk7GZWL._SL120_.jpg",
    "posted": true,
    "posted_at": "2026-03-24T18:56:02.008772+00:00",
    "created_at": "2026-03-24T05:26:09.674998+00:00"
  },
  {
    "ean": "8431890077230",
    "asin": "B0CH3HF49F",
    "name": "Sensodyne Cool Mint Mouthwash 500 ml (Pack of 2)",
    "supplier_cost": 3.816,
    "amazon_price": 17.74,
    "fees": 9.85,
    "profit": 4.073999999999999,
    "roi": 106.76100628930816,
    "estimated_sales": 10.0,
    "amazon_link": "https://www.amazon.fr/gp/product/B0CH3HF49F/ref=xx_dp_cont_revecalc",
    "supplier_link": "https://www.qogita.com/products/GmJAnBAvYd/sensodyne-cool-mint-mouthwash-500ml/",
    "sas_link": "https://sas.selleramp.com/sas/lookup?SasLookup%5Bsearch_term%5D=B0CH3HF49F",
    "image_url": "https://m.media-amazon.com/images/I/41qCwd1qKWL._SL120_.jpg",
    "posted": true,
    "posted_at": "2026-03-24T18:56:31.135988+00:00",
    "created_at": "2026-03-24T05:26:29.180168+00:00"
  },
  {
    "ean": "3401560154962",
    "asin": "B0G51XMR1S",
    "name": "Puressentiel - Essential Oils for Diffusion - Diffuse Provence - 100% pure and natural -Helps regain a feeling of comfort - 30 ml (Pack of 4)",
    "supplier_cost": 9.66,
    "amazon_price": 35.56,
    "fees": 11.04,
    "profit": 14.860000000000003,
    "roi": 153.83022774327125,
    "estimated_sales": 556.0,
    "amazon_link": "https://www.amazon.fr/gp/product/B0G51XMR1S/ref=xx_dp_cont_revecalc",
    "supplier_link": "https://www.qogita.com/products/YKW545/puressentiel-essential-oil-for-diffusion-provence-30ml/",
    "sas_link": "https://sas.selleramp.com/sas/lookup?SasLookup%5Bsearch_term%5D=B0G51XMR1S",
    "image_url": "https://m.media-amazon.com/images/I/41gVf8DELGL._SL120_.jpg",
    "posted": true,
    "posted_at": "2026-03-24T18:56:50.906247+00:00",
    "created_at": "2026-03-24T05:26:49.425321+00:00"
  },
  {
    "ean": "8700216179348",
    "asin": "B0CQKFPMRP",
    "name": "Always Discreet Incontinence Pads for Women 26 Pack Full Protection Incredible Discretion",
    "supplier_cost": 6.936,
    "amazon_price": 20.0,
    "fees": 10.24,
    "profit": 2.824,
    "roi": 40.71510957324106,
    "estimated_sales": 29.0,
    "amazon_link": "https://www.amazon.fr/gp/product/B0CQKFPMRP/ref=xx_dp_cont_revecalc",
    "supplier_link": "https://www.qogita.com/products/373ce11053294cbaa8fd732bdc884477/always-discreet-incontinence-pads-for-women-pack-of-26/",
    "sas_link": "https://sas.selleramp.com/sas/lookup?SasLookup%5Bsearch_term%5D=B0CQKFPMRP",
    "image_url": "https://m.media-amazon.com/images/I/51Dk8JzjJCL._SL120_.jpg",
    "posted": true,
    "posted_at": "2026-03-24T18:57:09.534002+00:00",
    "created_at": "2026-03-24T05:26:49.439834+00:00"
  },
  {
    "ean": "4007965112102",
    "asin": "B0013B5PT6",
    "name": "meridol Soft toothbrush for gums",
    "supplier_cost": 3.2640000000000002,
    "amazon_price": 9.05,
    "fees": 4.08,
    "profit": 1.7060000000000004,
    "roi": 52.26715686274511,
    "estimated_sales": 218.0,
    "amazon_link": "https://www.amazon.fr/gp/product/B0013B5PT6/ref=xx_dp_cont_revecalc",
    "supplier_link": "https://www.qogita.com/products/2ZY6RZ/meridol-gum-gentle-toothbrush/",
    "sas_link": "https://sas.selleramp.com/sas/lookup?SasLookup%5Bsearch_term%5D=B0013B5PT6",
    "image_url": "https://m.media-amazon.com/images/I/31DmZDWVxLL._SL120_.jpg",
    "posted": true,
    "posted_at": "2026-03-24T18:57:37.603594+00:00",
    "created_at": "2026-03-24T05:27:04.621443+00:00"
  },
  {
    "ean": "8009722011174",
    "asin": "B07CN6RDRN",
    "name": "Zincoseb Spray for Dogs and Cats | Sebum Regulating and Soothing Lotion | No Rinse | 200 ml | ICF",
    "supplier_cost": 13.452,
    "amazon_price": 26.95,
    "fees": 10.07,
    "profit": 3.427999999999999,
    "roi": 25.48319952423431,
    "estimated_sales": 22.0,
    "amazon_link": "https://www.amazon.fr/gp/product/B07CN6RDRN/ref=xx_dp_cont_revecalc",
    "supplier_link": "https://www.qogita.com/products/RLO9P6/nextmune-italy-srl-zincoseb-spray-200-ml/",
    "sas_link": "https://sas.selleramp.com/sas/lookup?SasLookup%5Bsearch_term%5D=B07CN6RDRN",
    "image_url": "https://m.media-amazon.com/images/I/41N54onejBL._SL120_.jpg",
    "posted": true,
    "posted_at": "2026-03-24T18:57:54.381180+00:00",
    "created_at": "2026-03-24T05:27:04.637765+00:00"
  },
  {
    "ean": "0073950111218",
    "asin": "B001NIZ5VM",
    "name": "Waterpik - 9852259 - Refill 2 Toothbrush Tips for WP 100",
    "supplier_cost": 6.648,
    "amazon_price": 23.98,
    "fees": 7.57,
    "profit": 9.762,
    "roi": 146.84115523465707,
    "estimated_sales": 12.0,
    "amazon_link": "https://www.amazon.fr/gp/product/B001NIZ5VM/ref=xx_dp_cont_revecalc",
    "supplier_link": "https://www.qogita.com/products/HDtp9SpiZc/waterpik-tb-100e-toothbrush-tips-for-water-flossers-2-pieces/",
    "sas_link": "https://sas.selleramp.com/sas/lookup?SasLookup%5Bsearch_term%5D=B001NIZ5VM",
    "image_url": "https://m.media-amazon.com/images/I/21JdahTn6EL._SL120_.jpg",
    "posted": true,
    "posted_at": "2026-03-24T18:58:21.311398+00:00",
    "created_at": "2026-03-24T05:27:46.449899+00:00"
  },
  {
    "ean": "3401579209561",
    "asin": "B008DGI0PA",
    "name": "PILEJE Lactibiane Tolerance 2.5G 30 Sobr",
    "supplier_cost": 19.02,
    "amazon_price": 49.99,
    "fees": 13.47,
    "profit": 17.500000000000004,
    "roi": 92.00841219768667,
    "estimated_sales": 8.0,
    "amazon_link": "https://www.amazon.fr/gp/product/B008DGI0PA/ref=xx_dp_cont_revecalc",
    "supplier_link": "https://www.qogita.com/products/4GMdwJF5Wf/pileje-lactibiane-tolerance-25g/",
    "sas_link": "https://sas.selleramp.com/sas/lookup?SasLookup%5Bsearch_term%5D=B008DGI0PA",
    "image_url": "https://m.media-amazon.com/images/I/41f-pCWQxPL._SL120_.jpg",
    "posted": false,
    "posted_at": null,
    "created_at": "2026-03-24T05:28:02.403937+00:00"
  },
  {
    "ean": "5029354010379",
    "asin": "B0CPF3RPF7",
    "name": "AloeDent Sensitive Toothpaste - Aloe Vera/Echinacea - Fluoride Free - 100ml (Pack of 3)",
    "supplier_cost": 5.3999999999999995,
    "amazon_price": 24.06,
    "fees": 9.28,
    "profit": 9.379999999999999,
    "roi": 173.7037037037037,
    "estimated_sales": 5.0,
    "amazon_link": "https://www.amazon.fr/gp/product/B0CPF3RPF7/ref=xx_dp_cont_revecalc",
    "supplier_link": "https://www.qogita.com/products/BNZnLLrjN3/madal-bal-madal-bal-sensitive-toothpaste-100ml/",
    "sas_link": "https://sas.selleramp.com/sas/lookup?SasLookup%5Bsearch_term%5D=B0CPF3RPF7",
    "image_url": "https://m.media-amazon.com/images/I/415BiZdc8lL._SL120_.jpg",
    "posted": false,
    "posted_at": null,
    "created_at": "2026-03-24T05:28:02.416681+00:00"
  },
  {
    "ean": "8006540882177",
    "asin": "B0G4VZC2HZ",
    "name": "Oral-B Glamour 3D White Advanced Luxe Perfection Against Surface Spots Designed for Advanced Teeth Brushing, Sweet Mint Arome, 75 ml (Pack of 2)",
    "supplier_cost": 2.208,
    "amazon_price": 9.78,
    "fees": 5.92,
    "profit": 1.6519999999999992,
    "roi": 74.8188405797101,
    "estimated_sales": 8.0,
    "amazon_link": "https://www.amazon.fr/gp/product/B0G4VZC2HZ/ref=xx_dp_cont_revecalc",
    "supplier_link": "https://www.qogita.com/products/83f18f9661f04e6790fcdc92e6906593/oral-b-3d-white-luxe-glamorous-white-toothpaste/",
    "sas_link": "https://sas.selleramp.com/sas/lookup?SasLookup%5Bsearch_term%5D=B0G4VZC2HZ",
    "image_url": "https://m.media-amazon.com/images/I/41bDmxLu2gL._SL120_.jpg",
    "posted": false,
    "posted_at": null,
    "created_at": "2026-03-24T05:28:23.225192+00:00"
  },
  {
    "ean": "4002590703985",
    "asin": "B00DRZHA1W",
    "name": "Pulmoll | Pulmoll Tablets | Since 1946 (Citron)",
    "supplier_cost": 2.664,
    "amazon_price": 10.79,
    "fees": 5.57,
    "profit": 2.5559999999999987,
    "roi": 95.9459459459459,
    "estimated_sales": 30.0,
    "amazon_link": "https://www.amazon.fr/gp/product/B00DRZHA1W/ref=xx_dp_cont_revecalc",
    "supplier_link": "https://www.qogita.com/products/63YDYD/pulmoll-lemon-and-vitamin-c-sugar-free-tablets-45g/",
    "sas_link": "https://sas.selleramp.com/sas/lookup?SasLookup%5Bsearch_term%5D=B00DRZHA1W",
    "image_url": "https://m.media-amazon.com/images/I/413N-rm2wIL._SL120_.jpg",
    "posted": false,
    "posted_at": null,
    "created_at": "2026-03-24T05:28:58.072885+00:00"
  },
  {
    "ean": "8700216179041",
    "asin": "B0CQKFLLXF",
    "name": "Always Discreet Ultimate Night Incontinence Pads for Women Extra Safe and Discreet Pack of 8",
    "supplier_cost": 2.916,
    "amazon_price": 15.13,
    "fees": 8.68,
    "profit": 3.534000000000001,
    "roi": 121.19341563786013,
    "estimated_sales": 7.0,
    "amazon_link": "https://www.amazon.fr/gp/product/B0CQKFLLXF/ref=xx_dp_cont_revecalc",
    "supplier_link": "https://www.qogita.com/products/50f1aa3800f245be9cf27afe7b8224db/always-discreet-incontinence-pads-for-women-ultimate-night/",
    "sas_link": "https://sas.selleramp.com/sas/lookup?SasLookup%5Bsearch_term%5D=B0CQKFLLXF",
    "image_url": "https://m.media-amazon.com/images/I/513mM1uFhJL._SL120_.jpg",
    "posted": false,
    "posted_at": null,
    "created_at": "2026-03-24T05:29:29.242104+00:00"
  },
  {
    "ean": "7610700600054",
    "asin": "B01MSUH2UF",
    "name": "Ricola Schweizer Kr\u00e4uterzucker Kr\u00e4uterbonbon, 250 g Sweets",
    "supplier_cost": 4.236,
    "amazon_price": 13.98,
    "fees": 8.38,
    "profit": 1.3639999999999999,
    "roi": 32.200188857412655,
    "estimated_sales": 21.0,
    "amazon_link": "https://www.amazon.fr/gp/product/B01MSUH2UF/ref=xx_dp_cont_revecalc",
    "supplier_link": "https://www.qogita.com/products/ACYLJmg3uT/ricola-herbal-candies-tin/",
    "sas_link": "https://sas.selleramp.com/sas/lookup?SasLookup%5Bsearch_term%5D=B01MSUH2UF",
    "image_url": "https://m.media-amazon.com/images/I/41VVywnKITL._SL120_.jpg",
    "posted": false,
    "posted_at": null,
    "created_at": "2026-03-24T05:29:43.287472+00:00"
  },
  {
    "ean": "8427426026773",
    "asin": "B005C8V0LI",
    "name": "HALITA - Tongue Scraper - Healthy Tongue - Daily Use - Fresh Breath - 1 unit per product",
    "supplier_cost": 2.5319999999999996,
    "amazon_price": 7.98,
    "fees": 4.0,
    "profit": 1.4480000000000008,
    "roi": 57.187993680884716,
    "estimated_sales": 10.0,
    "amazon_link": "https://www.amazon.fr/gp/product/B005C8V0LI/ref=xx_dp_cont_revecalc",
    "supplier_link": "https://www.qogita.com/products/CscSyXFA2y/halita-tongue-cleaner/",
    "sas_link": "https://sas.selleramp.com/sas/lookup?SasLookup%5Bsearch_term%5D=B005C8V0LI",
    "image_url": "https://m.media-amazon.com/images/I/41HPrzDrv8L._SL120_.jpg",
    "posted": false,
    "posted_at": null,
    "created_at": "2026-03-24T05:30:07.647510+00:00"
  },
  {
    "ean": "0070942304566",
    "asin": "B00ZA81VSM",
    "name": "GUM SOFT-PICKS Interdental Brushes Large 2 x 40 Pieces",
    "supplier_cost": 5.46,
    "amazon_price": 12.74,
    "fees": 5.83,
    "profit": 1.4500000000000002,
    "roi": 26.556776556776562,
    "estimated_sales": 6.0,
    "amazon_link": "https://www.amazon.fr/gp/product/B00ZA81VSM/ref=xx_dp_cont_revecalc",
    "supplier_link": "https://www.qogita.com/products/733QMowsCz/gum-soft-picks-original-interdental-brush-metal-free-large-40-picks/",
    "sas_link": "https://sas.selleramp.com/sas/lookup?SasLookup%5Bsearch_term%5D=B00ZA81VSM",
    "image_url": "https://m.media-amazon.com/images/I/51HOz-05xzL._SL120_.jpg",
    "posted": false,
    "posted_at": null,
    "created_at": "2026-03-24T05:30:07.765946+00:00"
  },
  {
    "ean": "5060176670723",
    "asin": "B00TOC427W",
    "name": "Dr. Organic Pomegranate Toothpaste 100 ml",
    "supplier_cost": 5.255999999999999,
    "amazon_price": 19.97,
    "fees": 8.65,
    "profit": 6.063999999999999,
    "roi": 115.37290715372907,
    "estimated_sales": 12.0,
    "amazon_link": "https://www.amazon.fr/gp/product/B00TOC427W/ref=xx_dp_cont_revecalc",
    "supplier_link": "https://www.qogita.com/products/43t7ZkAnTU/dr-organic-pomegranate-toothpaste-100ml/",
    "sas_link": "https://sas.selleramp.com/sas/lookup?SasLookup%5Bsearch_term%5D=B00TOC427W",
    "image_url": "https://m.media-amazon.com/images/I/41Se63xA3DL._SL120_.jpg",
    "posted": false,
    "posted_at": null,
    "created_at": "2026-03-24T05:30:07.787402+00:00"
  },
  {
    "ean": "0073950173445",
    "asin": "B00HU4RX4A",
    "name": "Waterpik - Compact Replacement Heads for Sensonic Electric Toothbrush and Complete Care, Pack of 3 (SRSB-3E)",
    "supplier_cost": 10.752,
    "amazon_price": 32.95,
    "fees": 8.99,
    "profit": 13.208,
    "roi": 122.84226190476191,
    "estimated_sales": 7.0,
    "amazon_link": "https://www.amazon.fr/gp/product/B00HU4RX4A/ref=xx_dp_cont_revecalc",
    "supplier_link": "https://www.qogita.com/products/F9AephAzAL/waterpik-brush-attachments-compact-sensonic-small-for-sr1000-and-sr3000-3-pieces/",
    "sas_link": "https://sas.selleramp.com/sas/lookup?SasLookup%5Bsearch_term%5D=B00HU4RX4A",
    "image_url": "https://m.media-amazon.com/images/I/319KfWIvH0L._SL120_.jpg",
    "posted": false,
    "posted_at": null,
    "created_at": "2026-03-24T05:30:07.829012+00:00"
  },
  {
    "ean": "8033875148043",
    "asin": "B084L5ZN7Z",
    "name": "Guna Oral suspension Enterosgel Tube, 225 g",
    "supplier_cost": 20.099999999999998,
    "amazon_price": 41.19,
    "fees": 12.29,
    "profit": 8.8,
    "roi": 43.78109452736319,
    "estimated_sales": 15.0,
    "amazon_link": "https://www.amazon.fr/gp/product/B084L5ZN7Z/ref=xx_dp_cont_revecalc",
    "supplier_link": "https://www.qogita.com/products/45d4f402277946199bb26b56cc9ab2a4/guna-oral-enterosgel-225g-tube/",
    "sas_link": "https://sas.selleramp.com/sas/lookup?SasLookup%5Bsearch_term%5D=B084L5ZN7Z",
    "image_url": "https://m.media-amazon.com/images/I/51tftZvu66L._SL120_.jpg",
    "posted": false,
    "posted_at": null,
    "created_at": "2026-03-24T05:30:07.876374+00:00"
  },
  {
    "ean": "3401599289857",
    "asin": "B0G529886C",
    "name": "Puressentiel Circulation Spray with 17 Essential Oils, 100 ml - Cooling Spray for Heavy Legs Relief in Just 15 Minutes - Ideal for Swollen Ankles, Swollen Feet - Suitable from 7 Years - (Pack of 2)",
    "supplier_cost": 11.28,
    "amazon_price": 27.0,
    "fees": 9.72,
    "profit": 6.000000000000002,
    "roi": 53.191489361702146,
    "estimated_sales": 58.0,
    "amazon_link": "https://www.amazon.fr/gp/product/B0G529886C/ref=xx_dp_cont_revecalc",
    "supplier_link": "https://www.qogita.com/products/KPzuHpK44k/puressentiel-circulation-express-tonic-spray-with-17-essential-oils-100-natural-100-ml/",
    "sas_link": "https://sas.selleramp.com/sas/lookup?SasLookup%5Bsearch_term%5D=B0G529886C",
    "image_url": "https://m.media-amazon.com/images/I/41WOKa4cL5L._SL120_.jpg",
    "posted": false,
    "posted_at": null,
    "created_at": "2026-03-24T05:30:35.952252+00:00"
  },
  {
    "ean": "8718951409798",
    "asin": "B08TLLNF43",
    "name": "Colgate - Toothbrush Max White Charcoal Soft 2pcs",
    "supplier_cost": 1.116,
    "amazon_price": 6.78,
    "fees": 3.93,
    "profit": 1.734,
    "roi": 155.3763440860215,
    "estimated_sales": 12.0,
    "amazon_link": "https://www.amazon.fr/gp/product/B08TLLNF43/ref=xx_dp_cont_revecalc",
    "supplier_link": "https://www.qogita.com/products/081f087a723c4b5dac611eb941b29fe0/colgate-spizzmax-white-carbon-2-pieces/",
    "sas_link": "https://sas.selleramp.com/sas/lookup?SasLookup%5Bsearch_term%5D=B08TLLNF43",
    "image_url": "https://m.media-amazon.com/images/I/41PuorRp67L._SL120_.jpg",
    "posted": false,
    "posted_at": null,
    "created_at": "2026-03-24T05:30:44.453735+00:00"
  },
  {
    "ean": "0070942503051",
    "asin": "B01DC0ZV26",
    "name": "Gum - Classic toothbrush with hard bristles",
    "supplier_cost": 2.364,
    "amazon_price": 8.99,
    "fees": 4.08,
    "profit": 2.5460000000000003,
    "roi": 107.69881556683589,
    "estimated_sales": 5.0,
    "amazon_link": "https://www.amazon.fr/gp/product/B01DC0ZV26/ref=xx_dp_cont_revecalc",
    "supplier_link": "https://www.qogita.com/products/NK0O0V/sunstar-gum-305-regular-brush-with-hard-bristles-assorted-colors/",
    "sas_link": "https://sas.selleramp.com/sas/lookup?SasLookup%5Bsearch_term%5D=B01DC0ZV26",
    "image_url": "https://m.media-amazon.com/images/I/310VwHhXP-L._SL120_.jpg",
    "posted": false,
    "posted_at": null,
    "created_at": "2026-03-24T05:32:32.766739+00:00"
  },
  {
    "ean": "4210201317838",
    "asin": "B08KSTWZ1Y",
    "name": "Oral-B FlossAction Electric Toothbrush Head with CleanMaximiser Technology - 2 Pieces",
    "supplier_cost": 7.548,
    "amazon_price": 18.29,
    "fees": 6.68,
    "profit": 4.061999999999999,
    "roi": 53.81558028616852,
    "estimated_sales": 5.0,
    "amazon_link": "https://www.amazon.fr/gp/product/B08KSTWZ1Y/ref=xx_dp_cont_revecalc",
    "supplier_link": "https://www.qogita.com/products/DXba5Uo7k6/oralb-oralb-floss-action-2u-refill-dental-floss/",
    "sas_link": "https://sas.selleramp.com/sas/lookup?SasLookup%5Bsearch_term%5D=B08KSTWZ1Y",
    "image_url": "https://m.media-amazon.com/images/I/319oT9EwKhL._SL120_.jpg",
    "posted": false,
    "posted_at": null,
    "created_at": "2026-03-24T05:33:50.841687+00:00"
  },
  {
    "ean": "3760269770942",
    "asin": "B09JX1WXJY",
    "name": "ISISPHARMA TEEN DERM \u2013 A.Z \u2013 Triple Action Anti-Blemish, Anti-Mark, Ultra Soothing, Combination to Oily Skin - With 15% Azelaic Acid - Made in France",
    "supplier_cost": 7.404,
    "amazon_price": 19.69,
    "fees": 8.59,
    "profit": 3.6960000000000015,
    "roi": 49.918962722852534,
    "estimated_sales": 300.0,
    "amazon_link": "https://www.amazon.fr/gp/product/B09JX1WXJY/ref=xx_dp_cont_revecalc",
    "supplier_link": "https://www.qogita.com/products/52cf56769d98422bbd51c0db14325a71/isispharma-teen-derm-az-triple-action-anti-imperfections/",
    "sas_link": "https://sas.selleramp.com/sas/lookup?SasLookup%5Bsearch_term%5D=B09JX1WXJY",
    "image_url": "https://m.media-amazon.com/images/I/31WfQaX9nnL._SL120_.jpg",
    "posted": false,
    "posted_at": null,
    "created_at": "2026-03-24T05:33:56.345830+00:00"
  },
  {
    "ean": "8801051294422",
    "asin": "B0CXMF5MFK",
    "name": "Oerich Toothpaste Set with Original Toothpaste 75ml x 4, Fluoride Free, Anti-Plaque, Antibacterial, Decay Protection, Fresh Mint Refreshment, Daily Dental Care in Emma",
    "supplier_cost": 3.168,
    "amazon_price": 22.49,
    "fees": 10.56,
    "profit": 8.761999999999997,
    "roi": 276.5782828282827,
    "estimated_sales": 42.0,
    "amazon_link": "https://www.amazon.fr/gp/product/B0CXMF5MFK/ref=xx_dp_cont_revecalc",
    "supplier_link": "https://www.qogita.com/products/88a6c35bfc4a49c8ac3172648b57dbe1/euthymol-original-toothpaste-75ml-gluten-free-no-fluoride-antibacterial-75ml/",
    "sas_link": "https://sas.selleramp.com/sas/lookup?SasLookup%5Bsearch_term%5D=B0CXMF5MFK",
    "image_url": "https://m.media-amazon.com/images/I/51UOIIdv-rL._SL120_.jpg",
    "posted": false,
    "posted_at": null,
    "created_at": "2026-03-24T05:34:00.586447+00:00"
  },
  {
    "ean": "8710103623168",
    "asin": "B00DQ5TMDC",
    "name": "Philips Sonicare HX8012/07 Pack of AirFloss Cannulas (X2)",
    "supplier_cost": 8.352,
    "amazon_price": 29.9,
    "fees": 8.49,
    "profit": 13.057999999999996,
    "roi": 156.34578544061299,
    "estimated_sales": 7.0,
    "amazon_link": "https://www.amazon.fr/gp/product/B00DQ5TMDC/ref=xx_dp_cont_revecalc",
    "supplier_link": "https://www.qogita.com/products/9f7a3940bc2e495da1688cdbc49ef161/philips-sonicare-airfloss-nozzles/",
    "sas_link": "https://sas.selleramp.com/sas/lookup?SasLookup%5Bsearch_term%5D=B00DQ5TMDC",
    "image_url": "https://m.media-amazon.com/images/I/41NQxhD-+rL._SL120_.jpg",
    "posted": false,
    "posted_at": null,
    "created_at": "2026-03-24T05:34:30.389742+00:00"
  },
  {
    "ean": "3014230002090",
    "asin": "B0G52KXKSZ",
    "name": "Signal Protecci\u00f3n Anticaries Pasta Toothpaste (Pack of 4)",
    "supplier_cost": 1.6320000000000001,
    "amazon_price": 15.36,
    "fees": 7.93,
    "profit": 5.798,
    "roi": 355.26960784313724,
    "estimated_sales": 69.0,
    "amazon_link": "https://www.amazon.fr/gp/product/B0G52KXKSZ/ref=xx_dp_cont_revecalc",
    "supplier_link": "https://www.qogita.com/products/b477523a7bf746389ded30f7f2b15f55/signal-dent-signal-anticaries-100/",
    "sas_link": "https://sas.selleramp.com/sas/lookup?SasLookup%5Bsearch_term%5D=B0G52KXKSZ",
    "image_url": "https://m.media-amazon.com/images/I/41HyFTu2-gL._SL120_.jpg",
    "posted": false,
    "posted_at": null,
    "created_at": "2026-03-24T05:34:50.449969+00:00"
  },
  {
    "ean": "3435172101175",
    "asin": "B01LHL84ZI",
    "name": "Quies Natural Wax Balls - Pack of 2 x 8 Pairs",
    "supplier_cost": 6.3,
    "amazon_price": 17.9,
    "fees": 7.2,
    "profit": 4.3999999999999995,
    "roi": 69.84126984126983,
    "estimated_sales": 11.0,
    "amazon_link": "https://www.amazon.fr/gp/product/B01LHL84ZI/ref=xx_dp_cont_revecalc",
    "supplier_link": "https://www.qogita.com/products/P187LZ/quies-boules-natural-wax-earplugs-8-pairs/",
    "sas_link": "https://sas.selleramp.com/sas/lookup?SasLookup%5Bsearch_term%5D=B01LHL84ZI",
    "image_url": "https://m.media-amazon.com/images/I/41G0J7HrBXL._SL120_.jpg",
    "posted": false,
    "posted_at": null,
    "created_at": "2026-03-24T05:35:19.165118+00:00"
  },
  {
    "ean": "3577056001383",
    "asin": "B07V9DZXX5",
    "name": "Inava Sensitivity Conical Toothbrush Set of 2",
    "supplier_cost": 4.308,
    "amazon_price": 18.2,
    "fees": 8.36,
    "profit": 5.532,
    "roi": 128.41225626740948,
    "estimated_sales": 24.0,
    "amazon_link": "https://www.amazon.fr/gp/product/B07V9DZXX5/ref=xx_dp_cont_revecalc",
    "supplier_link": "https://www.qogita.com/products/3cfe87b9120140109bf671debdd7f7df/inava-sensibilite-toothbrush-conical-branches/",
    "sas_link": "https://sas.selleramp.com/sas/lookup?SasLookup%5Bsearch_term%5D=B07V9DZXX5",
    "image_url": "https://m.media-amazon.com/images/I/31k841YtGnL._SL120_.jpg",
    "posted": false,
    "posted_at": null,
    "created_at": "2026-03-24T05:35:33.871823+00:00"
  }
]